{"title":"Combined feed","url":"https://FASHIONCORD.github.io/musinsa/all.xml","elements":[{"title":"6월 1주차 발매되는 신상품 리스트 (무신사 ─ 패션 뉴스)","contents":"엠엘비와 에스파의 만남을 비롯한 4가지 스페셜 컬래버레이션을 공개한다.","link":"https://www.musinsa.com/cms/news/view/1177","retrieved":1653650334804,"image":"https://image.musinsa.com/mfile_s01/_news/list629035469ccb3.jpg?v20220527170002"},{"title":"여름 트렌드 이끄는 10가지 서머 스니커즈 (무신사 ─ 패션 뉴스)","contents":"뉴발란스, 리프로덕션 오브 파운드가 대세 브랜드로 자리 잡았다.","link":"https://www.musinsa.com/cms/news/view/1176","retrieved":1653650334817,"image":"https://image.musinsa.com/mfile_s01/_news/list62903e9fc4931.jpg?v20220527170001"},{"title":"티셔츠 하나도 남다른 무신사 스탠다드 우먼즈 (무신사 ─ 패션 뉴스)","contents":"무신사 스탠다드가 다양한 실루엣과 컬러로 화사함을 선사할 우먼즈 신상품을 발매한다","link":"https://www.musinsa.com/cms/news/view/1175","retrieved":1653650334821,"image":"https://image.musinsa.com/mfile_s01/_news/list62903dfb61990.jpg?v20220527160001"},{"title":"입는 순간부터 시원한 무신사 스탠다드 (무신사 ─ 패션 뉴스)","contents":"접촉냉감 기능성을 가진 다양한 팬츠와 시원한 서머 아이템들을 가득 준비했다.","link":"https://www.musinsa.com/cms/news/view/1174","retrieved":1653650334825,"image":"https://image.musinsa.com/mfile_s01/_news/list62903d7b053c7.jpg?v20220527160001"},{"title":"포멀, 캐주얼 모두 정복할 파르티멘토 신상품 (무신사 ─ 패션 뉴스)","contents":"파르티멘토가 깔끔한 디자인으로 활용도 높은 다양한 상의 아이템을 선보인다.","link":"https://www.musinsa.com/cms/news/view/1172","retrieved":1653650334829,"image":"https://image.musinsa.com/mfile_s01/_news/list629034612671f.jpg?v20220527150001"},{"title":"요즘 힙은 이런 것! 서프앤터프 신상품 발매 (무신사 ─ 패션 뉴스)","contents":"스케이터, 길거리 사람들의 패션 등에서 영감을 얻은 서머 신상품을 선보인다.","link":"https://www.musinsa.com/cms/news/view/1170","retrieved":1653650334831,"image":"https://image.musinsa.com/mfile_s01/_news/list6290138cdb167.jpg?v20220527150001"},{"title":"보기만 해도 사이다! 버커루 쿨다잉 시리즈 (무신사 ─ 패션 뉴스)","contents":"보는 사람의 눈이 시원해지는 쿨다잉 시리즈 티셔츠 신상품을 눈여겨보자.","link":"https://www.musinsa.com/cms/news/view/1171","retrieved":1653650334833,"image":"https://image.musinsa.com/mfile_s01/_news/list629013dbec01a.jpg?v20220527150000"},{"title":"상큼 매력 뽐내는 아디다스 우신사 1, 2위 (무신사 ─ 패션 뉴스)","contents":"아스티어, 포럼 84 하이 스니커즈가 나란히 랭킹 1, 2위에 올랐다.","link":"https://www.musinsa.com/cms/news/view/1183","retrieved":1653630232794,"image":"https://image.musinsa.com/mfile_s01/_news/list62903a4a7d9f0.jpg?v"},{"title":"반 고흐의 해바라기를  티셔츠에 품은 팔렛 EVENT (무신사 ─ 패션 뉴스)","contents":"팔렛이 반 고흐, 르누아르의 작품을 소장한 내셔널갤러리와 협업 컬렉션을 발매한다.","link":"https://www.musinsa.com/cms/news/view/1169","retrieved":1653630232796,"image":"https://image.musinsa.com/mfile_s01/_news/list629028f64da1b.jpg?v20220527110001"},{"title":"서머 바이브로 충만한 리트리버클럽의 이색 협업 EVENT (무신사 ─ 패션 뉴스)","contents":"아메리칸 빈티지 감성을 교집합으로 삼아 페얼스 델리 앤 그로서리와 협업했다.","link":"https://www.musinsa.com/cms/news/view/1168","retrieved":1653630232800,"image":"https://image.musinsa.com/mfile_s01/_news/list6290285e15882.jpg?v20220527110001"},{"title":"아크메드라비로 완성한 리사의 Y2K 스타일 (무신사 ─ 패션 뉴스)","contents":"아크메드라비가 블랙핑크 리사를 새 브랜드 뮤즈로 선정하고 캠페인 화보를 선보인다.","link":"https://www.musinsa.com/cms/news/view/1165","retrieved":1653630232803,"image":"https://image.musinsa.com/mfile_s01/_news/list629027c5ea54a.jpg?v20220527110001"},{"title":"클래식&프레피 무드에 집중한 아웃스탠딩 (무신사 ─ 패션 뉴스)","contents":"22 서머 6차 신상품은 아메리칸 클래식 캐주얼 무드에 집중했다.","link":"https://www.musinsa.com/cms/news/view/1166","retrieved":1653630232805,"image":"https://image.musinsa.com/mfile_s01/_news/list629012d943e3e.jpg?v20220527110000"},{"title":"무더위 속에서도 세련된 룩 지키는 드로우핏 (무신사 ─ 패션 뉴스)","contents":"포멀, 클래식 감성을 유지하는 22 서머 신상품을 한정 발매한다.","link":"https://www.musinsa.com/cms/news/view/1167","retrieved":1653630232808,"image":"https://image.musinsa.com/mfile_s01/_news/list62901275b8f24.jpg?v20220527110000"},{"title":"재입고만을 기다렸다! 푸마 베이더론 1, 2위 (무신사 ─ 패션 뉴스)","contents":"과거의 실루엣과 미래적인 디테일을 결합한 베이더론이 인기다.","link":"https://www.musinsa.com/cms/news/view/1173","retrieved":1653630232809,"image":"https://image.musinsa.com/mfile_s01/_news/list62902bb603b63.jpg?v20220527104000"},{"title":"레전드 소환, 앤더슨벨 × 아식스 래플 시작 (무신사 ─ 패션 뉴스)","contents":"엄청난 인기를 누리는 협업 에디션을 무신사 래플로 한정 발매한다.","link":"https://www.musinsa.com/cms/news/view/1164","retrieved":1653630232813,"image":"https://image.musinsa.com/mfile_s01/_news/list62902177f1e1c.jpg?v20220527100001"},{"title":"우신사에서도 통한 우에라의 그리스 럭셔리 무드 (무신사 ─ 패션 뉴스)","contents":"국내 단독 론칭을 알린 우에라의 인기 셔츠가 우신사 랭킹 상위권에 올랐다.","link":"https://www.musinsa.com/cms/news/view/1155","retrieved":1653585965564,"image":"https://image.musinsa.com/mfile_s01/_news/list62900a3c0ac1d.jpg?v"},{"title":"그리스에서 온 럭셔리 브랜드, 우에라 입점 EVENT (무신사 ─ 패션 뉴스)","contents":"무신사 쇼케이스를 통해 우에라의 단독 론칭을 온라인으로 살펴보자.","link":"https://www.musinsa.com/cms/news/view/1156","retrieved":1653585965567,"image":"https://image.musinsa.com/mfile_s01/_news/list628f38dc48c27.jpg?v20220526210001"},{"title":"국내 단독 론칭하는 럭셔리 브랜드의 정체는? EVENT (무신사 ─ 패션 뉴스)","contents":"그리스에서 시작한 하이엔드 브랜드 우에라를 무신사 라이브로 소개한다.","link":"https://www.musinsa.com/cms/news/view/1154","retrieved":1653556842878,"image":"https://image.musinsa.com/mfile_s01/_news/list628f2d9400e4f.jpg?v20220526180001"},{"title":"올여름 트렌드 니트! 인템포무드로 확인하자 (무신사 ─ 패션 뉴스)","contents":"트렌드 아이템으로 주목받는 서머 니트 웨어를 다양하게 준비했다.","link":"https://www.musinsa.com/cms/news/view/1153","retrieved":1653553593112,"image":"https://image.musinsa.com/mfile_s01/_news/list628f24351441e.jpg?v20220526170005"},{"title":"다음 중 마음에 드는 플립플랍은? 인기템 모음 (무신사 ─ 패션 뉴스)","contents":"가볍고 자유로운 착용감이 매력적인 인기 플립플랍 톱 10을 소개한다.","link":"https://www.musinsa.com/cms/news/view/1152","retrieved":1653553593114,"image":"https://image.musinsa.com/mfile_s01/_news/list628f305300497.jpg?v20220526170004"},{"title":"여름의 찬란한 순간을 담은 인기 향수 톱 10 (무신사 ─ 패션 뉴스)","contents":"상큼한 여름을 만들어 줄 우신사 인기 향수 10가지를 소개한다.","link":"https://www.musinsa.com/cms/news/view/1151","retrieved":1653553593131,"image":"https://image.musinsa.com/mfile_s01/_news/list628f2bb5ec341.jpg?v20220526170003"},{"title":"골프공 캐릭터로 골프 랭킹 정복한 브랜드는? (무신사 ─ 패션 뉴스)","contents":"5월 3주차 무신사 골프 랭킹에 오른 대세 아이템들을 소개한다.","link":"https://www.musinsa.com/cms/news/view/1150","retrieved":1653553593132,"image":"https://image.musinsa.com/mfile_s01/_news/list628f248f9efd1.jpg?v20220526170002"},{"title":"입는 순간부터 시원한 시그니처의 서머 컬렉션 (무신사 ─ 패션 뉴스)","contents":"냉감 기능성 소재로 제작한 반소매, 팬츠 아이템을 셋업으로 구성해 선보인다.","link":"https://www.musinsa.com/cms/news/view/1149","retrieved":1653553593134,"image":"https://image.musinsa.com/mfile_s01/_news/list628f10e5a374a.jpg?v20220526150002"},{"title":"애슬레저 룩 선사할 무신사 아울렛 인기템은? (무신사 ─ 패션 뉴스)","contents":"최대 80% 할인 혜택으로 아디다스, 니티드 등의 인기 아이템을 만날 수 있다.","link":"https://www.musinsa.com/cms/news/view/1148","retrieved":1653553593136,"image":"https://image.musinsa.com/mfile_s01/_news/list628f108f17d42.jpg?v20220526150000"},{"title":"[진행] 온라인MD 채용 (무신사 ─ 구인)","contents":"예일","link":"https://www.musinsa.com/mz/brandrecruit/view/2603","retrieved":1653882024353,"image":"https://image.musinsa.com/mfile_s01/_brand/free_medium/yale.png?202205261150"},{"title":"[진행] 마케터 모집 공고 (무신사 ─ 구인)","contents":"본챔스","link":"https://www.musinsa.com/mz/brandrecruit/view/2602","retrieved":1653882024356,"image":"https://image.musinsa.com/mfile_s01/_brand/free_medium/bornchamps.png?202205191058"},{"title":"[진행] (주)레시피그룹 온라인 브랜드 MD 모집 (경력직) (무신사 ─ 구인)","contents":"니티드","link":"https://www.musinsa.com/mz/brandrecruit/view/2601","retrieved":1653882024363,"image":"https://image.musinsa.com/mfile_s01/_brand/free_medium/knitted.png?202205101506"},{"title":"[진행] (주)어반시티 CS 고객관리 담당자 채용 (무신사 ─ 구인)","contents":"어반디타입","link":"https://www.musinsa.com/mz/brandrecruit/view/2600","retrieved":1653882024369,"image":"https://image.musinsa.com/mfile_s01/_brand/free_medium/urbandtype.png?202205121629"},{"title":"[진행] [진행] 아카이브 볼드 AMD&CS 채용 (무신사 ─ 구인)","contents":"아카이브 볼드","link":"https://www.musinsa.com/mz/brandrecruit/view/2599","retrieved":1653882024369,"image":"https://image.musinsa.com/mfile_s01/_brand/free_medium/archivebold.png?202205121608"},{"title":"[진행] 꼼파뇨 물류 입출고 및 CS관리 업무 (무신사 ─ 구인)","contents":"꼼파뇨","link":"https://www.musinsa.com/mz/brandrecruit/view/2598","retrieved":1653882024375,"image":"https://image.musinsa.com/mfile_s01/_brand/free_medium/compagno.png?202205121422"},{"title":"[진행] 꼼파뇨 그래픽 디자이너 직원 채용 (무신사 ─ 구인)","contents":"꼼파뇨","link":"https://www.musinsa.com/mz/brandrecruit/view/2597","retrieved":1653882024375,"image":"https://image.musinsa.com/mfile_s01/_brand/free_medium/compagno.png?202205121422"},{"title":"[진행] 아코스튜디오 웹디자이너(경력) 모집 (무신사 ─ 구인)","contents":"아코스튜디오스페이스","link":"https://www.musinsa.com/mz/brandrecruit/view/2596","retrieved":1653882024376,"image":"https://image.musinsa.com/mfile_s01/_brand/free_medium/aqostudiospace.png?202205231112"},{"title":"[진행] SSRL MD/CS 채용 (신입/경력) (무신사 ─ 구인)","contents":"에스에스알엘","link":"https://www.musinsa.com/mz/brandrecruit/view/2595","retrieved":1653882024380,"image":"https://image.musinsa.com/mfile_s01/_brand/free_medium/ssrl.png?202203031540"},{"title":"[진행] CS 경력 채용 (무신사 ─ 구인)","contents":"코드그라피","link":"https://www.musinsa.com/mz/brandrecruit/view/2594","retrieved":1653882024384,"image":"https://image.musinsa.com/mfile_s01/_brand/free_medium/codegraphy.png?202205121626"},{"title":"[진행] 마케터/AMD 채용 (무신사 ─ 구인)","contents":"브라운브레스","link":"https://www.musinsa.com/mz/brandrecruit/view/2593","retrieved":1653882024384,"image":"https://image.musinsa.com/mfile_s01/_brand/free_medium/brownbreath.png?202205261151"},{"title":"[진행] 웹디자이너 채용 (무신사 ─ 구인)","contents":"써틴먼스","link":"https://www.musinsa.com/mz/brandrecruit/view/2592","retrieved":1653373566614,"image":"https://image.musinsa.com/mfile_s01/_brand/free_medium/13month.png?202204221625"},{"title":"[진행] 도미넌트  디자이너 경력직 채용 (무신사 ─ 구인)","contents":"도미넌트","link":"https://www.musinsa.com/mz/brandrecruit/view/2591","retrieved":1653373566621,"image":"https://image.musinsa.com/mfile_s01/_brand/free_medium/dominant.png?202205121725"},{"title":"[진행] 도미넌트 그래픽 디자이너 / 웹디자이너 모집 (무신사 ─ 구인)","contents":"도미넌트","link":"https://www.musinsa.com/mz/brandrecruit/view/2590","retrieved":1653373566622,"image":"https://image.musinsa.com/mfile_s01/_brand/free_medium/dominant.png?202205121725"},{"title":"[진행] 그래픽 디자이너 채용 (무신사 ─ 구인)","contents":"카멜워크","link":"https://www.musinsa.com/mz/brandrecruit/view/2589","retrieved":1653373566624,"image":"https://image.musinsa.com/mfile_s01/_brand/free_medium/camelwork.png?202203031547"},{"title":"[진행] 디자이너 부문 경력직 채용 [4년차 이상] (무신사 ─ 구인)","contents":"비욘드클로젯","link":"https://www.musinsa.com/mz/brandrecruit/view/2588","retrieved":1653373566627,"image":"https://image.musinsa.com/mfile_s01/_brand/free_medium/beyondcloset.png?202205171336"},{"title":"[진행] 블론드나인 신입/경력 AMD 채용 (무신사 ─ 구인)","contents":"블론드나인","link":"https://www.musinsa.com/mz/brandrecruit/view/2587","retrieved":1653373566628,"image":"https://image.musinsa.com/mfile_s01/_brand/free_medium/blond9.png?202205201125"},{"title":"[진행] [진행] [경력] 온라인 경력직 MD 구인 (무신사 ─ 구인)","contents":"23.65","link":"https://www.musinsa.com/mz/brandrecruit/view/2586","retrieved":1653373566630,"image":"https://image.musinsa.com/mfile_s01/_brand/free_medium/2365.png?202205241216"},{"title":"[진행] 패션 브랜드 수아레 - 온라인MD 구인 (무신사 ─ 구인)","contents":"수아레","link":"https://www.musinsa.com/mz/brandrecruit/view/2585","retrieved":1653373566631,"image":"https://image.musinsa.com/mfile_s01/_brand/free_medium/suare.png?202205181334"},{"title":"[진행] 유니폼브릿지 CS/AMD 신입 추가모집 (무신사 ─ 구인)","contents":"유니폼브릿지","link":"https://www.musinsa.com/mz/brandrecruit/view/2584","retrieved":1653373566632,"image":"https://image.musinsa.com/mfile_s01/_brand/free_medium/uniformbridge.png?202205161336"},{"title":"[진행] 브랜드 WaiKei(와이케이)에서 운영팀(물류관리 및 온라인스토어 운영, CS업무)을 모집합니다. (무신사 ─ 구인)","contents":"와이케이","link":"https://www.musinsa.com/mz/brandrecruit/view/2583","retrieved":1653373566637,"image":"https://image.musinsa.com/mfile_s01/_brand/free_medium/waikei.png?202205251331"},{"title":"[진행] 스타일 디자이너 경력자 구인 (무신사 ─ 구인)","contents":"론즈데일","link":"https://www.musinsa.com/mz/brandrecruit/view/2582","retrieved":1653359353290,"image":"https://image.musinsa.com/mfile_s01/_brand/free_medium/lonsdale1.png?202205260952"},{"title":"[진행] 디아프바인 AMD 1명 / CREW 1명 ( 경력 무관) (무신사 ─ 구인)","contents":"디아프바인","link":"https://www.musinsa.com/mz/brandrecruit/view/2581","retrieved":1653359353291,"image":"https://image.musinsa.com/mfile_s01/_brand/free_medium/diafvine.png?202205241413"},{"title":"[진행] 패션 디자이너 경력직 채용 공고 (무신사 ─ 구인)","contents":"맥우드건","link":"https://www.musinsa.com/mz/brandrecruit/view/2580","retrieved":1653359353300,"image":"https://image.musinsa.com/mfile_s01/_brand/free_medium/magoodgan.png?202106251602"},{"title":"[진행] 의류브랜드 라퍼지스토어 배너 팀원 채용진행합니다. (무신사 ─ 구인)","contents":"라퍼지 포 우먼","link":"https://www.musinsa.com/mz/brandrecruit/view/2579","retrieved":1653359353302,"image":"https://image.musinsa.com/mfile_s01/_brand/free_medium/lafudgeforwomen.png?202204051515"},{"title":"[진행] 의류브랜드 라퍼지스토어 마케터 채용진행합니다. (무신사 ─ 구인)","contents":"라퍼지스토어","link":"https://www.musinsa.com/mz/brandrecruit/view/2578","retrieved":1653359353303,"image":"https://image.musinsa.com/mfile_s01/_brand/free_medium/lafudgestore.png?202205181136"},{"title":"[진행] 의류브랜드 라퍼지스토어 배송 및 물류 직원 채용진행합니다 (무신사 ─ 구인)","contents":"라퍼지스토어","link":"https://www.musinsa.com/mz/brandrecruit/view/2577","retrieved":1653359353305,"image":"https://image.musinsa.com/mfile_s01/_brand/free_medium/lafudgestore.png?202205181136"},{"title":"[진행] 의류브랜드 라퍼지스토어 리터치 팀원 채용진행합니다. (무신사 ─ 구인)","contents":"라퍼지스토어","link":"https://www.musinsa.com/mz/brandrecruit/view/2576","retrieved":1653359353307,"image":"https://image.musinsa.com/mfile_s01/_brand/free_medium/lafudgestore.png?202205181136"},{"title":"[진행] AMD 채용 (무신사 ─ 구인)","contents":"에즈이프 캘리","link":"https://www.musinsa.com/mz/brandrecruit/view/2575","retrieved":1653359353309,"image":"https://image.musinsa.com/mfile_s01/_brand/free_medium/asifcalie.png?202205121642"},{"title":"[진행] 마케팅 직원 채용합니다 (무신사 ─ 구인)","contents":"탱그램팩토리","link":"https://www.musinsa.com/mz/brandrecruit/view/2574","retrieved":1653359353311,"image":"https://image.musinsa.com/mfile_s01/_brand/free_medium/tangramfactory.png?202204121721"},{"title":"<여성 샌들 코디> 본격적인 샌들의 계절! 이제 스니커즈는 넣어두세요 (네이버 포스트 ─ 무신사)","contents":"본격적인 샌들의 계절! 이제 스니커즈는 넣어두세요 날씨가 슬슬 더워지고 있습니다. 올여름은 역대급 폭염이 찾아올 것이란 예보도 있죠.여름 관련 아이템 수요가 급증하고 있습니다.많은 여름 아이템 중 가장 먼저···","link":"https://m.post.naver.com/viewer/postView.naver?volumeNo=33882433&memberNo=22191262","retrieved":1653906317773,"image":"https://post-phinf.pstatic.net/MjAyMjA1MzBfNjkg/MDAxNjUzODkyNDk1MzU4.pxGfm9cJHd85PvGBri99ghqOYv4i3F5P8-S4C39fV4sg.To6kGBo0P-btDwP83lZ4f6ShoXPZuG4aXI2ZBQcYZikg.JPEG/IDlT_wYansMs2WTUzbwkIZDmJbY8.jpg?type=fb500_195"},{"title":"<블러셔 추천> 뷰티 인플루언서들의 두 뺨을 물들인 투쿨포스쿨의 신상 블러셔! (네이버 포스트 ─ 무신사)","contents":"러블리함이 샘솟는 뷰티 인플루언서들의 메이크업에서 빠지지 않고 등장하는 녀석, 투쿨포스쿨의 신상 아트클래스 바이로댕 블러쉬 빔 듀오! 어딘가 모르게 메이크업이 허전하다고 느껴지거나 메이크업할 때 블러셔···","link":"https://m.post.naver.com/viewer/postView.naver?volumeNo=33867672&memberNo=22191262","retrieved":1653622196527,"image":"https://post-phinf.pstatic.net/MjAyMjA1MjdfMjYg/MDAxNjUzNjE1MTE0NzM3.YQQnDhnwAc67ApTTuhA0Ec2HM-i0NbzVPjdzf9XV6_Ag.-0voBcDoRPXYc6Ddr8N50rgNlH8BtdMIf4mg1HQjx7Qg.JPEG/IKRPEWOjuOCoBbcMFiq-FHsi2pl4.jpg?type=fb500_195"},{"title":"<여름 가방 추천>서머 시즌을 위한 가방&슈즈 추천 10 (네이버 포스트 ─ 무신사)","contents":"덜어낼수록 쾌적해지는 서머 시즌.서머 시즌을 위한 백&amp;슈즈 10 서머 시즌의 무드를 확실하게 구분해주는 아이템은? 바로, 백&amp;슈즈 아이템! 서머 시즌에만 활용할 수 있는 실루엣과 소재부터 쿨하게 즐길 수···","link":"https://m.post.naver.com/viewer/postView.naver?volumeNo=33858428&memberNo=22191262","retrieved":1653474324213,"image":"https://post-phinf.pstatic.net/MjAyMjA1MjVfMTg5/MDAxNjUzNDY3ODE1ODQ4.JtJGUhZySI5yHzmKnhcofXKugYVl_qBY0MZGoj0l8sEg.GR4pDD7WqnHm_coP2crW7Vr85PGgEPmTZ1eAjlO8c4wg.JPEG/InxI9zofO9XTt_qH0wsDrIgzlBSM.jpg?type=fb500_195"},{"title":"<우주소녀 보나> 러블리한 여름을 락피쉬웨더웨어, 우주소녀 보나와 함께! (네이버 포스트 ─ 무신사)","contents":"이렇게 사랑스럽다면, 올 여름 행복할 것 같아요. 우주소녀 보나와 락피쉬웨더워어의 만남무더운 여름을 대표하는 아이템을 떠올리면 티셔츠와 같은 짧은 소매의 옷이 생각납니다. 하지만 여름에는 장마가 있기 때문···","link":"https://m.post.naver.com/viewer/postView.naver?volumeNo=33832480&memberNo=22191262","retrieved":1653359369446,"image":"https://post-phinf.pstatic.net/MjAyMjA1MjBfMjMg/MDAxNjUzMDI5MjUwNTY3.U5L43mLgMAMGAfHwqm4qaezBOlMjRNlsXXfI-XVd9K4g.QmKovNN7nbgwvKa2Y8I2xP9rk5f4EzHJWHTIec-Y1zwg.JPEG/IR3zv-2dJZ1IUShhCtLKODh7GNyg.jpg?type=fb500_195"},{"title":"<데님 팬츠 추천> 언제입어도 좋은 데님 팬츠! 좋은 가격에 득템하자 (네이버 포스트 ─ 무신사)","contents":"언제입어도 좋은 데님 팬츠 무신사 아울렛에서 찾아보자!데님 팬츠는 옷장에 누구나 하나쯤은 가지고 있는 아이템입니다. 사계절 내내 입을 수 있는 효자 아이템이죠. 오늘은 무신사 아울렛에서 찾은 가성비 좋은 데···","link":"https://m.post.naver.com/viewer/postView.naver?volumeNo=33826081&memberNo=22191262","retrieved":1653359369446,"image":"https://post-phinf.pstatic.net/MjAyMjA1MTlfMTUx/MDAxNjUyOTQyNDY3OTUx.jq2YhCtzghjzK_FibmSRtrLYVeTPSJRNRrqzqusE6pwg.ZZBsRxotTz8u4IwiBsx8MobfYXOuE6BRjxf5QYDQ0Scg.JPEG/IZwDUa3GNtPdDN4pcXEsgDINO7wQ.jpg?type=fb500_195"},{"title":"<크록스 코디> 여름 필수 아이템! 크록스로 꾸민 다양한 코디 모음 (네이버 포스트 ─ 무신사)","contents":"곧 찾아올 크록스의 계절! 이렇게 코디하세요 날이 더워지자 샌들의 인기가 높아지고 있습니다. 샌들이 인기를 끌면 자연스래 주목하게 되는 브랜드가 있죠? 바로 크록스입니다. 저렴한 가격, 엄청난 편안함, 귀여운···","link":"https://m.post.naver.com/viewer/postView.naver?volumeNo=33819132&memberNo=22191262","retrieved":1653359369450,"image":"https://post-phinf.pstatic.net/MjAyMjA1MThfOTEg/MDAxNjUyODU2MTgzNDU5.T7Y8sGDlJBpMojqfLVBGucOTII4SVqm5UjqHgKeU-YMg.lRXyXwrD60u-8pZbppe5Ed9LsvVR_DDO-vmnMzQqsUMg.JPEG/IWE00-dJvmbFRjPPyTZmOv5JPocY.jpg?type=fb500_195"},{"title":"<폴로 셔츠 추천> 미국 대통령들이 취임식에서 입었던 브랜드는? (네이버 포스트 ─ 무신사)","contents":"격이 다른 정통 아메리칸 클래식! 브룩스 브라더스지금은 바야흐로 폴로 셔츠의 시대! 트렌드에 상관없이 꾸준히 우리 곁을 지킨 클래식 아이템입니다. 최근 들어 90년대 스타일의 유행으로 그 당시 유행했던 프레피···","link":"https://m.post.naver.com/viewer/postView.naver?volumeNo=33812888&memberNo=22191262","retrieved":1653359369450,"image":"https://post-phinf.pstatic.net/MjAyMjA1MTdfNzgg/MDAxNjUyNzcxMjM2MTYx.LcKdHy6wEcFDnNJPYg-p1-vmYKiJiKcNYKACgpXykogg.3ktbUEGRmkK4WIRFJoDKcNSJgbh515PBBQRs0DL7C7Qg.JPEG/IOH4Is7dd1Si6bdbJSJJkoaL4niQ.jpg?type=fb500_195"},{"title":"<원피스 추천> 인생샷 선사할 우신사 대세 원피스 TOP 10! (네이버 포스트 ─ 무신사)","contents":"상큼한 서머 룩을 위해 원피스를 고민하고 있다면? 여성들의 영원한 스테디셀러이자변함없이 사랑받는 아이템이 있습니다.바로 원피스!상하의를 매칭할 필요가 없으니바쁜 아침, 고민과 시간을줄여주는 꿀템이기도 ···","link":"https://m.post.naver.com/viewer/postView.naver?volumeNo=33793506&memberNo=22191262","retrieved":1653359369458,"image":"https://post-phinf.pstatic.net/MjAyMjA1MTNfMTY0/MDAxNjUyNDI2MjY4MDM4.GmDH62wIXvhQChsq25urKo-tllRyfHi86BIGE6DlBqQg.mDdWw3SQBnRETKERESr2Jn2kKJRZeZIdSxy_4ZGaskog.JPEG/I-voVcM8Fuuc_5xPzPVLHeUvFfsQ.jpg?type=fb500_195"},{"title":"<아디다스 운동화> 아디다스와 친환경이 만났다! 아디다스 x 팔리 협업 스니커즈 (네이버 포스트 ─ 무신사)","contents":"아디다스가 지향하는 친환경의 모습!아디다스 x 팔리 협업 스니커즈 환경을 생각하는 브랜드와 산업군이 갈수록 증가하고 있습니다. 종이를 재활용하는 것은 기본이고, 기름으로만 움직일 수 있던 차가 이제는 전기···","link":"https://m.post.naver.com/viewer/postView.naver?volumeNo=33792935&memberNo=22191262","retrieved":1653359369458,"image":"https://post-phinf.pstatic.net/MjAyMjA1MTNfMTk5/MDAxNjUyNDIwNTIyNjg3.cOok5LU1WsnXXQ9u-hZ2YqFMv8yZgLWEXuTGpCPgRSQg.M52heH7b-drbCzZLkws-AeqE4woZbYXoCXXrZ5Nwim0g.JPEG/ILoKza942SW4sCKLQvlB-li7LRA0.jpg?type=fb500_195"},{"title":"<반바지 추천> 반바지의 계절! 무신사 아울렛 가성비 반바지 모음 (네이버 포스트 ─ 무신사)","contents":"반바지의 계절! 무신사 아울렛 가성비 반바지 모음 낮 최고기온은 28도까지 올라가는 등 초여름 날씨를 보이고 있습니다.이제 반바지를 꺼내 입어도 전혀 어색하지 않은 날씨!롱 슬리브 티셔츠와 반바지 조합으로 입···","link":"https://m.post.naver.com/viewer/postView.naver?volumeNo=33787211&memberNo=22191262","retrieved":1652351194225,"image":"https://post-phinf.pstatic.net/MjAyMjA1MTJfODMg/MDAxNjUyMzMyOTI0NDQ2.UlQUwzC_JlzjA-MpdmmSdlkdlL7j3SG0m9rc3QVh4Nog.06x0NzCiFpfvkZ5an3pw0Sf9Mjz0iy-5pqJIR1UryXAg.JPEG/IgO8kUGijVbtXTwXWwfPihtNA55A.jpg?type=fb500_195"},{"title":"<엠엘비 청키 라이너> 엠엘비의 2만5천 족 완판 베스트셀러, 청키 라이너 (네이버 포스트 ─ 무신사)","contents":"완연한 봄 날씨가 이어지는 요즘, 새 신발로 기분 전환하고 싶으시죠? 그산뜻한 컬러 웨이로 선보이는&nbsp;엠엘비의 2만5천 족 완판 베스트셀러,&nbsp;청키 라이너를 추천합니다!투박하고 트렌디한 어글리 슈즈 디자인으로 엄···","link":"https://m.post.naver.com/viewer/postView.naver?volumeNo=33779790&memberNo=22191262","retrieved":1652264708371,"image":"https://post-phinf.pstatic.net/MjAyMjA1MTFfMTI2/MDAxNjUyMjQ4ODQ3NzIy.BGiASKt7ajyA8C8HRDh2Iyiq-ODNG-E2CW0XyWJrV4wg.WG0mc47BRmIa5iQM-JBmwxSTae_wCQo_cGp44lWCg90g.JPEG/IuXza4AH1i5u8t0VUoLvPINvSsHE.jpg?type=fb500_195"},{"title":"<샌들 추천> 미리 준비하자! 여름의 특권, 샌들 코디 모음 (네이버 포스트 ─ 무신사)","contents":"날씨가 슬슬 더워지는 걸 보니,&nbsp;이번&nbsp;여름은&nbsp;무척&nbsp;빨리 찾아올 모양입니다.다가올&nbsp;여름 가장 먼저 챙겨할 아이템은 바로 샌들!&nbsp;가볍게&nbsp;신기&nbsp;좋고,&nbsp;시원하고, 멋 까지 보장하는 여름철 필수 아이템!오늘은 샌들로 꾸···","link":"https://m.post.naver.com/viewer/postView.naver?volumeNo=33771684&memberNo=22191262","retrieved":1652178195637,"image":"https://post-phinf.pstatic.net/MjAyMjA1MTBfMTE1/MDAxNjUyMTUwMTA3NTAz.G1-l2j28mO603LoL0U10T2TMRRJNaAsEmOskCOlKoXcg.WwDuOsx3nNfHkyxoILi1KJdrUeJg5ezj1IFvvpK55Kcg.JPEG/IGyeGq_SAnJrjHybnr91q4M-KD3I.jpg?type=fb500_195"},{"title":"<남자 향수> 옷 스타일에 맞는 다양한 남자 향수 추천! (네이버 포스트 ─ 무신사)","contents":"무신사 크루가 알려주는 스타일링에 맞는 남자 향수 선택법 캐주얼 룩에 어울리는 향수가 따로 있을까요? 머리에서부터 발끝까지 완벽하게 코디해도 정작 옷 스타일과 어울리지 않는 향을&nbsp;선택한다면 오히려 마이너···","link":"https://m.post.naver.com/viewer/postView.naver?volumeNo=33766200&memberNo=22191262","retrieved":1652091898684,"image":"https://post-phinf.pstatic.net/MjAyMjA1MDlfMTMz/MDAxNjUyMDc3MjAxMjcx.B98iju9ylayNV_u_yn94tDuKm5sVcpAG1ajx4hqdZVMg.4HfuzBxqzlVIuqyU0J7poYdbFF0l2rLZ2JyXy6XAgWMg.JPEG/IlzqS-GIA8Ic6YeXXRJyHMaXNJE8.jpg?type=fb500_195"},{"title":"<클락스 왈라비> 유행을 넘어 클래식으로! 클락스 왈라비 추천 (네이버 포스트 ─ 무신사)","contents":"클락스를 대표하는 왈라비! 무신사에서 찾은 멋진 왈라비 모음 클락스는 1825년에 영국 남서부 마을에서 시작한 약 200년 전통의 슈즈 브랜드입니다. 모든 사람들의 발에 꼭 맞는 수제화를 제작하겠다는 신념으로 지···","link":"https://m.post.naver.com/viewer/postView.naver?volumeNo=33744416&memberNo=22191262","retrieved":1651918995817,"image":"https://post-phinf.pstatic.net/MjAyMjA1MDRfODQg/MDAxNjUxNjQ3OTAxMTc5.V18dPMcVhtvquRO22e0uTROUjRpeGmLZzEuCIyn-kFog.f5B_Eo1M1P6OeTOfi7I237NX1z7KRXDugpMWhRg1678g.JPEG/IgsEqdBRIO2mmHFIew_9l8PtJUAc.jpg?type=fb500_195"},{"title":"<메이크업 브랜드 추천> 더 가치 있게, 컬러풀하게 빛내줄 비건 메이크업! (네이버 포스트 ─ 무신사)","contents":"비건 메이크업, 도전해볼까?더 가치 있게, 컬러풀하게 빛내줄 비건 메이크업 제품을 소개합니다 요즘 음식과&nbsp;패션에&nbsp;이어&nbsp;뷰티에도&nbsp;'비건'&nbsp;바람이&nbsp;불고&nbsp;있습니다.&nbsp;하지만&nbsp;아직까지&nbsp;'비건&nbsp;제품은 접근하···","link":"https://m.post.naver.com/viewer/postView.naver?volumeNo=33741823&memberNo=22191262","retrieved":1651832674871,"image":"https://post-phinf.pstatic.net/MjAyMjA1MDRfMTA1/MDAxNjUxNjMxODQyNTQ0.mn1iXut8wdT3Wei8R9ttRpac-X-yIYGxUxzUKLahnsAg.GBB5x98W8kK4pCsKyrNcHDRkH7XpGpMJv8LR0bujCmUg.JPEG/IzmpozKDA3kg5Vsrm_NGMpUEyJZI.jpg?type=fb500_195"},{"title":"<역시즌 패딩> 저렴할 때 사두자! 무신사 아울렛에서 찾은 역시즌 명품 패딩 (네이버 포스트 ─ 무신사)","contents":"무신사 아울렛에서 찾은 역시즌 명품 패딩! 계절이 봄을&nbsp;지나&nbsp;여름을&nbsp;향해&nbsp;달려가고&nbsp;있습니다. 이런 시기에 겨울 아이템인 패딩을싸게&nbsp;살&nbsp;수&nbsp;있다는&nbsp;사실&nbsp;알고&nbsp;계셨나요?바로 역시즌 세일 때문인데요!역시즌이란 말 ···","link":"https://m.post.naver.com/viewer/postView.naver?volumeNo=33743548&memberNo=22191262","retrieved":1651746249274,"image":"https://post-phinf.pstatic.net/MjAyMjA1MDRfMTg1/MDAxNjUxNjQyMTMxMTYy.mLlylZ9WjzUnEemvIIwTb-GY9AJFRame2VXMAVdhUjUg.KKGijflXQTORz-Dvobdbgn8pvtdiGJpFeInLHapy0EQg.JPEG/IzM085lU9qnItIPdESQxzA-pWS2I.jpg?type=fb500_195"},{"title":"[슬리퍼 추천] 곧 여름이야! 여름 필수템 슬리퍼 코디 모음 (네이버 포스트 ─ 무신사)","contents":"&nbsp;아직은 선선하지만&nbsp;눈 깜짝할 사이에 여름이 찾아올 거예요.날이 더워지면&nbsp;제일 먼저 떠오르는 아이템, 슬리퍼!가볍게 신기 좋고, 시원하여 여름철 반드시 필요한 녀석입니다.슬리퍼를 잠깐 집 앞 편의점 갈 때, 동···","link":"https://m.post.naver.com/viewer/postView.naver?volumeNo=33735473&memberNo=22191262","retrieved":1651659879504,"image":"https://post-phinf.pstatic.net/MjAyMjA1MDNfMTQ5/MDAxNjUxNTUyOTA4NjE5.j73u5bDREkBoQIVbo6BlycHgjdXcxJQ8QqIQcs0LTDAg.uwb1Z1KFb7RB-xzeetAiW_vpQczIzUurun3nXYZXC2Eg.JPEG/IvvVEBhE2l_m_Yk-T8kpy9xnKToM.jpg?type=fb500_195"},{"title":"<어린이날 선물> 뭐 사줘야 할까? 무신사 키즈에서 골라보자 (네이버 포스트 ─ 무신사)","contents":"미리 준비하는 어린이날 선물! 무신사 키즈에서 골라보자 일 년에 한 번뿐인 아이들의 축제, 어린이 날!소중한 선물을 해주고 싶은 마음이 클 수밖에 없습니다.더군다나 아이의 개월 수에 따라 필요한 물품이 달라 ···","link":"https://m.post.naver.com/viewer/postView.naver?volumeNo=33736925&memberNo=22191262","retrieved":1651573671262,"image":"https://post-phinf.pstatic.net/MjAyMjA1MDNfMjYz/MDAxNjUxNTY0MTgwODgy.IMjiKFU8kCeo-9ne7TLGuS33MDDp8PMv33u-mzDG0Hwg.GaQtmi_bz7PrMhj-HWkwiDyxQNXBDQfuEYVxK2IOuX8g.JPEG/Ijtaltsqm9ZQgz1L1YM3qxhUGJ58.jpg?type=fb500_195"},{"title":"<가방 추천> 준비만으로도 설렌다! 여행 가방 추천 열 가지 (네이버 포스트 ─ 무신사)","contents":"설레는 여행 준비 필수템! 여행 가방 추천 열 가지 사회적 거리두기 해제를 시작으로, 잊고 있던 일상이 차츰 돌아오고 있습니다.모두가 가장 그리웠던 건 바로 자유로운 '여행'이 아닐까요? 여행을 준비하기 위한 ···","link":"https://m.post.naver.com/viewer/postView.naver?volumeNo=33727684&memberNo=22191262","retrieved":1651487163609,"image":"https://post-phinf.pstatic.net/MjAyMjA1MDJfNCAg/MDAxNjUxNDY5NjE2ODM5.7np6oy3qNLb5PMC933hXPhsNlbZHedAbjtFVrMnPIp8g.WRoV_52cekRvCBlr4fMXr-NSZQhYjdvTf-nt4nUda8Ag.JPEG/IKoeTTOQq9Zx04hHv3u-eIojGnQc.jpg?type=fb500_195"},{"title":"[독일군 스니커즈] 필수 소장 스니커즈! 거리에서 만난 독일군 스니커즈 (네이버 포스트 ─ 무신사)","contents":"클래식은 영원하다! 거리에서 만난 독일군 스니커즈  캐주얼룩부터 포멀한 차림까지두루 잘 어울리는 독일군 스니커즈!독일군 스니커즈는 실제로 1970년대 독일 연방군에서 보급되는 활동화입니다.진짜 군인들이 신···","link":"https://m.post.naver.com/viewer/postView.naver?volumeNo=33706771&memberNo=22191262","retrieved":1651314167812,"image":"https://post-phinf.pstatic.net/MjAyMjA0MjhfMTI3/MDAxNjUxMTMxODg4NTE2.S83wvmEoJXL8-uW_jZCNMWxGBlMkwzWz_NX7ns2eiOUg.3yodnBjCc4jXObrYcVrKj7H0mtEpZg7JwUYBSQilXhAg.JPEG/I-61_TIa7rEVGjYTKgw5o8N-soKo.jpg?type=fb500_195"},{"title":"겨울에도 컬러 포기 못해! FCMM의 숏 패딩 (네이버 포스트 ─ 무신사 ─ 무신사 스냅)","contents":"<span class=\"ell\">무신사</span>","link":"https://post.naver.com/viewer/postView.naver?volumeNo=33035895&memberNo=22191262&navigationType=push","retrieved":1640871132406,"image":"https://post-phinf.pstatic.net/MjAyMTEyMzBfMjMw/MDAxNjQwODI3MzQ4Mzky.jg1lSxtY_7GB7PghX1b-kheOegkoAvUcgyG3PEPxNVUg.2AFc_2fhCW7gqlJENgvi6vzNxVyMmcsQwg-5I0euzJIg.JPEG/Ik7eH871xK9-XGHwmCZq17-a8sF0.jpg?type=fb500_500"},{"title":"러블리 무드 가득한 우먼 데일리 룩! (네이버 포스트 ─ 무신사 ─ 무신사 스냅)","contents":"<span class=\"ell\">무신사</span>","link":"https://post.naver.com/viewer/postView.naver?volumeNo=33035855&memberNo=22191262&navigationType=push","retrieved":1640852959860,"image":"https://post-phinf.pstatic.net/MjAyMTEyMzBfMjMx/MDAxNjQwODI2MjQ4Nzgy.VEIoqNkkPoruMQ3rll6UIpxWgLhY_cVQWsxGUdhFY6Eg.hg7BVDCpZLHvNWn9GPA9kSK2UiS1wDyBkGnftWcc_b8g.JPEG/IQeHu4P7dnM6U64vTUBSP9H3g27I.jpg?type=fb500_500"},{"title":"포멀한 느낌의 남자 출근 룩 모아보기 (네이버 포스트 ─ 무신사 ─ 무신사 스냅)","contents":"<span class=\"ell\">무신사</span>","link":"https://post.naver.com/viewer/postView.naver?volumeNo=33035691&memberNo=22191262&navigationType=push","retrieved":1640830555938,"image":"https://post-phinf.pstatic.net/MjAyMTEyMzBfMjcw/MDAxNjQwODI0NjU1MTIx.TH1_u3EEGdTAlpdBbXe9oajseDdg2qOxcw8xQROr710g.yCrdSDSvAPf-76BTOFaJaJMMNLnQv7VNGtP7SsFTImIg.JPEG/ITdaNUhHV5qhrSpzhCVd4uaR4w9I.jpg?type=fb500_500"},{"title":"꾸안꾸 룩에는 역시 무채색이지! (네이버 포스트 ─ 무신사 ─ 무신사 스냅)","contents":"<span class=\"ell\">무신사</span>","link":"https://post.naver.com/viewer/postView.naver?volumeNo=33029331&memberNo=22191262&navigationType=push","retrieved":1640766570973,"image":"https://post-phinf.pstatic.net/MjAyMTEyMjlfMjQ1/MDAxNjQwNzQwODk5NDg0.u4ziiTgnJbhM78vgLvL22phGlHisVMiDnK7xkxCzYbQg.ZXZDB44tWND4VBwxwTYn_yMOQcCFI5xkNb1vdqroE4wg.JPEG/Iml6I3BR9QXbrhQynmMLWvzDxHR0.jpg?type=fb500_500"},{"title":"따뜻함과 디자인 모두 챙긴 유니크한 퀼팅 패딩 (네이버 포스트 ─ 무신사 ─ 무신사 스냅)","contents":"<span class=\"ell\">무신사</span>","link":"https://post.naver.com/viewer/postView.naver?volumeNo=33029282&memberNo=22191262&navigationType=push","retrieved":1640744087247,"image":"https://post-phinf.pstatic.net/MjAyMTEyMjlfMTg2/MDAxNjQwNzQwNTI2ODU1.JNc2AhfBO3WCR0bZZoys58d2-PgoK_aelXhJUacDTHIg.1v4VYcyxUw3QgE1JQrAxQYdYO0pVGSMul5QFyl954usg.JPEG/I_AuMebzn7yZZ7NwzSpgIsRpu0WE.jpg?type=fb500_500"},{"title":"휘뚜루마뚜루 입기 좋은 트레이닝 셋업 추천 (네이버 포스트 ─ 무신사 ─ 무신사 스냅)","contents":"<span class=\"ell\">무신사</span>","link":"https://post.naver.com/viewer/postView.naver?volumeNo=33022154&memberNo=22191262&navigationType=push","retrieved":1640680223514,"image":"https://post-phinf.pstatic.net/MjAyMTEyMjhfMjE4/MDAxNjQwNjUyNTIyNDA0.V-wp2buxqM22ef2rolv8r0h6H7NWOV653RvMEE-zbLcg.GMgUm00wM372dneGJz6yNhZopBfMScFX9ftnGMkBjwMg.JPEG/IpF-PYKHvQzMl25K7OTRenqH3UAw.jpg?type=fb500_500"},{"title":"라퍼지 포 우먼 패딩으로 따뜻한 겨울 보내는 법 (네이버 포스트 ─ 무신사 ─ 무신사 스냅)","contents":"<span class=\"ell\">무신사</span>","link":"https://post.naver.com/viewer/postView.naver?volumeNo=33021974&memberNo=22191262&navigationType=push","retrieved":1640657788710,"image":"https://post-phinf.pstatic.net/MjAyMTEyMjhfMTk0/MDAxNjQwNjUwNzk0MDc1.TTkFZczE02D_rZW92W5q0q_OG4o0w4YUvU6_q7WtOz8g.2zGC9onHROvwofYU8oPPqtQjleNPRUJ67U8RP82mK64g.JPEG/IYIMaahejgrwoBDdauID8ofZ1_nk.jpg?type=fb500_500"},{"title":"코디의 마무리는 깔끔한 푸마 스니커즈로! (네이버 포스트 ─ 무신사 ─ 무신사 스냅)","contents":"<span class=\"ell\">무신사</span>","link":"https://post.naver.com/viewer/postView.naver?volumeNo=33015454&memberNo=22191262&navigationType=push","retrieved":1640619704129,"image":"https://post-phinf.pstatic.net/MjAyMTEyMjdfMjcz/MDAxNjQwNTY2OTU0MDA2.SUrsWvH8kwUGnRmNcBsHuYLiFnQKmI-G-gVRmorkS8Mg._q9EHvBmOQ8kzJFSuqcBUBNNptj2tkha3lwzXLo6-1Qg.JPEG/IMZDUCpdO0gPhpZkmh-8MpQ4kLVw.jpg?type=fb500_500"},{"title":"캐주얼하면서 힙하게! 캐트릿 코디 모음 (네이버 포스트 ─ 무신사 ─ 무신사 스냅)","contents":"<span class=\"ell\">무신사</span>","link":"https://post.naver.com/viewer/postView.naver?volumeNo=33015387&memberNo=22191262&navigationType=push","retrieved":1640593889127,"image":"https://post-phinf.pstatic.net/MjAyMTEyMjdfNDIg/MDAxNjQwNTY2NTgzNTk3.Rhg0h2JAX-fQoJCLHG85GKQPx98X9OVn894T5fgEIpwg.lrc6YpDHHATavbbZEUhqObCj6vC6v1whigcJ0iqJYq4g.JPEG/ItYkts8Jsh3Nzr2eQRFWMmjZ8Gko.jpg?type=fb500_500"},{"title":"와이드 팬츠와 오버롤로 완성한 꾸러기 룩 (네이버 포스트 ─ 무신사 ─ 무신사 스냅)","contents":"<span class=\"ell\">무신사</span>","link":"https://post.naver.com/viewer/postView.naver?volumeNo=33015332&memberNo=22191262&navigationType=push","retrieved":1640571384721,"image":"https://post-phinf.pstatic.net/MjAyMTEyMjdfMjEw/MDAxNjQwNTY2MTczNTg4.wRt0n_YR0BLnjWk1xLix3liDxBUhx_6XkCWx1kkLvoUg.8TPFx2iPTgb9TwMoFj6t-le0JNcPlacicCp_YjDgPMEg.JPEG/IcxSPAvS-ZXZS0nbgn-fDYZY_qnE.jpg?type=fb500_500"},{"title":"나에게 어울리는 패턴은? 패턴 캐주얼 룩 모음 (네이버 포스트 ─ 무신사 ─ 무신사 스냅)","contents":"<span class=\"ell\">무신사</span>","link":"https://post.naver.com/viewer/postView.naver?volumeNo=32999798&memberNo=22191262&navigationType=push","retrieved":1640312127434,"image":"https://post-phinf.pstatic.net/MjAyMTEyMjNfMjE3/MDAxNjQwMjQ4MTYxMDUx._FRW2SlVDC38a58uy_YkauASOf4C2lgeItBmOw9yrTIg.jM9uRHK0nEhvNUIIs26fzdBkDe6FPymjmfVEinnzRrYg.JPEG/IR-iH-s5xL3KhKRWJkoeYeTfJ3V0.jpg?type=fb500_500"},{"title":"크리스마스 이브에 입기 좋은 남자 댄디 룩! (네이버 포스트 ─ 무신사 ─ 무신사 스냅)","contents":"<span class=\"ell\">무신사</span>","link":"https://post.naver.com/viewer/postView.naver?volumeNo=32999724&memberNo=22191262&navigationType=push","retrieved":1640334607249,"image":"https://post-phinf.pstatic.net/MjAyMTEyMjNfMjc3/MDAxNjQwMjQ4Mzk3NTMz.mlgE9BDc7C8euP8r8nZ0J6jfTSUTKi1lEap8Ma5mgqcg.vxkwbIuanQ5IZ1Ctw36DFkYkkLkdm-6DiPYJJcnv4yYg.JPEG/IQnoy0BTRDoEhUTPwYvCyAB7zgAo.jpg?type=fb500_500"},{"title":"스타일과 수납력까지 뚝딱 해결해주는 백팩 (네이버 포스트 ─ 무신사 ─ 무신사 스냅)","contents":"<span class=\"ell\">무신사</span>","link":"https://post.naver.com/viewer/postView.naver?volumeNo=32995795&memberNo=22191262&navigationType=push","retrieved":1640266341022,"image":"https://post-phinf.pstatic.net/MjAyMTEyMjNfMTEx/MDAxNjQwMjIwMDM5MjE5.YJ1ZEhn-5cVjs8JYpHyj4sq5ok5-rUhZ1qaOQBG17ysg.tMIW5xkrOEBVKNOq18kgb0fd2J9rODD-T_QCpVsF398g.JPEG/I81v_M3r3iVnN5SejJErkwV1HI-k.jpg?type=fb500_500"},{"title":"같은 옷 맞아요? 네파의 리버서블 아우터 (네이버 포스트 ─ 무신사 ─ 무신사 스냅)","contents":"<span class=\"ell\">무신사</span>","link":"https://post.naver.com/viewer/postView.naver?volumeNo=32995671&memberNo=22191262&navigationType=push","retrieved":1640248164897,"image":"https://post-phinf.pstatic.net/MjAyMTEyMjNfMjc3/MDAxNjQwMjE5NjI1NzM4.jlC-pd1yhaZ9j6-2L5Sr86v0PPf225wYPZjXuczHt00g.FfOiBmC60H_P3IdNNO1Z8yFASvpotTodz5VtcfXktBMg.JPEG/I5Wjy-YavdRYB-nOm-ZM81KrYPwE.jpg?type=fb500_500"},{"title":"편안한 게 최고야 원 마일 웨어 홀릭! (네이버 포스트 ─ 무신사 ─ 무신사 스냅)","contents":"<span class=\"ell\">무신사</span>","link":"https://post.naver.com/viewer/postView.naver?volumeNo=32995628&memberNo=22191262&navigationType=push","retrieved":1640225742649,"image":"https://post-phinf.pstatic.net/MjAyMTEyMjNfMTky/MDAxNjQwMjE5MTUzOTM3.uVEfCAag8jA5dRlJ0J6XXlJWq1znGU85DoiDgGZU4_Qg.-HJYab_F7nxckWppwllCMXLznhSdQ47YSwUZ7QRSRoog.JPEG/I4hf8eTwm4VMzVBWzhzrPTCboSJs.jpg?type=fb500_500"},{"title":"올겨울 코디 블랙&화이트 이것만 기억해. (네이버 포스트 ─ 무신사 ─ 무신사 스냅)","contents":"<span class=\"ell\">무신사</span>","link":"https://post.naver.com/viewer/postView.naver?volumeNo=32989018&memberNo=22191262&navigationType=push","retrieved":1640161841797,"image":"https://post-phinf.pstatic.net/MjAyMTEyMjJfMTUg/MDAxNjQwMTM1OTM0MTU0.UEtPQQsaDwL29W87So0L-DqR9DXqvxh6DpfoQBZUjL8g.HEid4purjLjA4xnW57LsGbSlWaov9hebfhRAMZYCX58g.JPEG/IxvIMxu4g560FCLRPXv33kLfvu4E.jpg?type=fb500_500"},{"title":"데님 팬츠 하나로 일주일 코디 끝내기 (네이버 포스트 ─ 무신사 ─ 무신사 스냅)","contents":"<span class=\"ell\">무신사</span>","link":"https://post.naver.com/viewer/postView.naver?volumeNo=32988931&memberNo=22191262&navigationType=push","retrieved":1640141053077,"image":"https://post-phinf.pstatic.net/MjAyMTEyMjJfNTkg/MDAxNjQwMTM1Njc4NzM3.8vlC-srxivOxleZBISQeGRWOnc7GrjhbhrGePjWoRwwg.tTQhsnSP5kc7fT2q8RyC52sWDm-7rGQapE5_qSl20ysg.JPEG/IfOTCiwPUod_OSfvo-UEccDJcijM.jpg?type=fb500_500"},{"title":"명불허전 데님 맛집! 리바이스 코디는 이렇게 (네이버 포스트 ─ 무신사 ─ 무신사 스냅)","contents":"<span class=\"ell\">무신사</span>","link":"https://post.naver.com/viewer/postView.naver?volumeNo=32982413&memberNo=22191262&navigationType=push","retrieved":1640054643302,"image":"https://post-phinf.pstatic.net/MjAyMTEyMjFfMjI2/MDAxNjQwMDUyMjcxNDQw.ifJKmTglyQ0K8gQo6QvTKssUlXKd7cDQKiXiANOHzTEg.9BKFLgF8KnLlIErYibdVN2b2B_JzMM5n6XHLPWA5eF8g.JPEG/I7xBOiQSDmCz-jhA3A5VimLfxtpk.jpg?type=fb500_500"},{"title":"스케이트 타기 좋은 힙한 스트릿 코디 (네이버 포스트 ─ 무신사 ─ 무신사 스냅)","contents":"<span class=\"ell\">무신사</span>","link":"https://post.naver.com/viewer/postView.naver?volumeNo=32974407&memberNo=22191262&navigationType=push","retrieved":1640007179917,"image":"https://post-phinf.pstatic.net/MjAyMTEyMjBfMjMy/MDAxNjM5OTYxODAxODE2.xIirInjvd6AjaKU9tA8aAnsyFcvWzgD-_Xa9x4CKQh8g.1Dee7NtyDGGsiEjT_3gTsW8J2BFpSYyGqM45o5-Jozcg.JPEG/I-alekmGOFHXgU1L1H_R3vFh1zKk.jpg?type=fb500_500"},{"title":"클래식한 가방과 함께 출근 룩 고민 끝! (네이버 포스트 ─ 무신사 ─ 무신사 스냅)","contents":"<span class=\"ell\">무신사</span>","link":"https://post.naver.com/viewer/postView.naver?volumeNo=32974352&memberNo=22191262&navigationType=push","retrieved":1639988962430,"image":"https://post-phinf.pstatic.net/MjAyMTEyMjBfOTcg/MDAxNjM5OTYxMDA0ODg3.hgS17QHiGa12HaoIVWY4e8kMpdtvByZUZ06S0qwFerYg.CELeyLU4Z6W6rqnK2Zicg0Aii85zQeunHJ9tGV-MYAgg.JPEG/IYECEESwHoYJ1cTdqOfg_gZn6KpY.jpg?type=fb500_500"},{"title":"설 연휴 필수 아이템! 연휴를 더욱 알차게 해줄 꿀템은? (네이버 포스트 ─ 무신사 ─ 무신사 리포트)","contents":"<span class=\"ell\">무신사</span>","link":"https://post.naver.com/viewer/postView.naver?volumeNo=33205145&memberNo=22191262&navigationType=push","retrieved":1643451936897,"image":"https://post-phinf.pstatic.net/MjAyMjAxMjhfMTEw/MDAxNjQzMzM1ODUxNDQz.3GKBmtn8NEBOUNpwn2d21kNbFsyWVronzcuKPVE1qzAg.gWFbsg0oFj10RmyefvF9wrd44MeTzYoJcCNBvmndH1kg.JPEG/IeXynkYEB_Pn5bBrxvkl7hM3nDYc.jpg?type=fb500_500"},{"title":"크로스 백 메신저 백 랭킹. 무신사에서 큰 인기를 얻은 가방을 확인하자 (네이버 포스트 ─ 무신사 ─ 무신사 리포트)","contents":"<span class=\"ell\">무신사</span>","link":"https://post.naver.com/viewer/postView.naver?volumeNo=33164845&memberNo=22191262&navigationType=push","retrieved":1642749849193,"image":"https://post-phinf.pstatic.net/MjAyMjAxMjFfMjY3/MDAxNjQyNzQwNjY2NzAw.aMzcpKXURYLVrRxvsqtSsKz4wL8UyFjPYL9PKGdOMbEg.xvpKYLYKTB54BLH9NfdMRTUF2XwVSkgSNF5z9h_kMdcg.JPEG/IBy9U6BXqcxskDRwynrlEvybRmto.jpg?type=fb500_500"},{"title":"겨울 등산 스노보드를 즐길 때 필요한 아이템은? 에디터가 직접 알려준다! (네이버 포스트 ─ 무신사 ─ 무신사 리포트)","contents":"<span class=\"ell\">무신사</span>","link":"https://post.naver.com/viewer/postView.naver?volumeNo=33163949&memberNo=22191262&navigationType=push","retrieved":1642746436235,"image":"https://post-phinf.pstatic.net/MjAyMjAxMjFfMTI1/MDAxNjQyNzMyODc0OTAy.i2DlmZu-5u9FqntMfzJokIKtKkwHEc2VOxIro8Ibw0kg.SzbkLspZtDSzmIVqynlKHPDRmL2RqBvuomv9Nm1r2nwg.JPEG/IFneAbV0D8P3u32vPBgkY_RJEeUs.jpg?type=fb500_500"},{"title":"패딩 부터 다운 팬츠까지! 보온&기능성 끝판왕 브랜드 타이온 (네이버 포스트 ─ 무신사 ─ 무신사 리포트)","contents":"<span class=\"ell\">무신사</span>","link":"https://post.naver.com/viewer/postView.naver?volumeNo=33158975&memberNo=22191262&navigationType=push","retrieved":1642670725459,"image":"https://post-phinf.pstatic.net/MjAyMjAxMjBfMTIx/MDAxNjQyNjU5NzYwNjAz.Pn3_c4Ye9kbgXFRz5bV8iseSf8X2Hl1UetzHmqRkClwg.hE-8lEVx5_seYCoIqvF1QkwWMVmObRydYYRBl87QBUAg.JPEG/IVRRURLRUY95mRCrLFHee3w0zTFc.jpg?type=fb500_500"},{"title":"발라클라바 요즘 유행하는 인기 모자! 어떤 녀석들이 잘 팔릴까? (네이버 포스트 ─ 무신사 ─ 무신사 리포트)","contents":"<span class=\"ell\">무신사</span>","link":"https://post.naver.com/viewer/postView.naver?volumeNo=33158498&memberNo=22191262&navigationType=push","retrieved":1642663537275,"image":"https://post-phinf.pstatic.net/MjAyMjAxMjBfMTE1/MDAxNjQyNjU3ODcyMzYy.Xn5bFqZbWuMlng2HqKO8JD5A209wIIxMso_sqT-4ezog.rutgNolanKctsVcsrbL3tZfZSq35SzJHy4_VgGTDsPEg.JPEG/IADK_3vq4IMrs43Wos-qzkofwYEg.jpg?type=fb500_500"},{"title":"허니제이 스우파로 대박난 그녀가 만든 패션 브랜드! (네이버 포스트 ─ 무신사 ─ 무신사 리포트)","contents":"<span class=\"ell\">무신사</span>","link":"https://post.naver.com/viewer/postView.naver?volumeNo=33138252&memberNo=22191262&navigationType=push","retrieved":1642408291443,"image":"https://post-phinf.pstatic.net/MjAyMjAxMTdfMjYw/MDAxNjQyMzk4MTUyOTYz.Eh5OPbOLdiqxjrsSfr9LMBa8jxRbyDryNxjaZPUIL_gg.02_l7pyH89wXZBmJ0u5DvXHU_iDXItjA48lt5RkWPF8g.JPEG/IeD8l2kogDOaISqOv4z-dklGJyhs.jpg?type=fb500_500"},{"title":"골프 고수가 되려면, 준비부터 철저해야 한다. 골프백 추천 아이템! (네이버 포스트 ─ 무신사 ─ 무신사 리포트)","contents":"<span class=\"ell\">무신사</span>","link":"https://post.naver.com/viewer/postView.naver?volumeNo=33118092&memberNo=22191262&navigationType=push","retrieved":1642058704803,"image":"https://post-phinf.pstatic.net/MjAyMjAxMTNfMjg1/MDAxNjQyMDQ5NjgwNzY1.4QFzvjv65qP7W7N7c_VmuZOeaTvUeTds-fP2a5qxtdgg.6WtTDMMFQkg2thy0O3eY3mJHn5-i2R9wVG2ui8nPd_gg.JPEG/IeJu5aOxkKbE9uqREMMOC4CIQUI4.jpg?type=fb500_500"},{"title":"롱 코트만한 겨울 아우터는 없다고 봐! 가볍게 입어도, 갖춰 입어도 그저 멋스럽다 (네이버 포스트 ─ 무신사 ─ 무신사 리포트)","contents":"<span class=\"ell\">무신사</span>","link":"https://post.naver.com/viewer/postView.naver?volumeNo=33104457&memberNo=22191262&navigationType=push","retrieved":1641889810634,"image":"https://post-phinf.pstatic.net/MjAyMjAxMTFfNzcg/MDAxNjQxODgxMjQ2NDkz.JZyVGck-Pm7s-AAUkzJrpm1ldEPMgUvqPZlVqj0u5RIg.bvr1uuebSRnAvUn_1nAk5JfjCk7R9SMfg95DkgTKDKwg.JPEG/IFCeqGKTgH7_yu4kCkWoY4o5TVR0.jpg?type=fb500_500"},{"title":"겨우내 든든하게 옷장을 채워줄 무신사 스탠다드의 아이템을 소개한다 (네이버 포스트 ─ 무신사 ─ 무신사 리포트)","contents":"<span class=\"ell\">무신사</span>","link":"https://post.naver.com/viewer/postView.naver?volumeNo=33083658&memberNo=22191262&navigationType=push","retrieved":1641690768133,"image":"https://post-phinf.pstatic.net/MjAyMjAxMDdfOSAg/MDAxNjQxNTMwMjI5OTMy.Fvy08aTC3sDpCO2yYHBcVGM2zkkLQyvOoL7NHNykMQMg.Q90_5ItsFRIFypprYpn2vuAfRwfqo8GU-avQj0qYvFkg.JPEG/IDpPpnUGOrPf_MQX-A-SAMfi_2Bo.jpg?type=fb500_500"},{"title":"여름 쿨톤 찰떡템, 다 모았다! 여쿨 에디터의 #왓츠_인_마이_파우치 (네이버 포스트 ─ 무신사 ─ 무신사 리포트)","contents":"<span class=\"ell\">무신사</span>","link":"https://post.naver.com/viewer/postView.naver?volumeNo=33083200&memberNo=22191262&navigationType=push","retrieved":1641623372679,"image":"https://post-phinf.pstatic.net/MjAyMjAxMDdfNzUg/MDAxNjQxNTI1Mjg5MDcz.MpLkJFliwxjbUgox_dRp4vukt4HvEU_EblpGYQut1F8g.NmySnJOTX5QDuWikWEj0TuRiSkP70RCi1uQglkDLF4Qg.JPEG/IbAh5bndI9wIuNoOxfrxkapV99ww.jpg?type=fb500_500"},{"title":"새해에는 더욱 열심히 운동하기! 새해를 맞아 운동하기 좋은 아이템을 한데 모았다. (네이버 포스트 ─ 무신사 ─ 무신사 리포트)","contents":"<span class=\"ell\">무신사</span>","link":"https://post.naver.com/viewer/postView.naver?volumeNo=33077681&memberNo=22191262&navigationType=push","retrieved":1641457818462,"image":"https://post-phinf.pstatic.net/MjAyMjAxMDZfMTEw/MDAxNjQxNDUwNDMwMDkw.uDDuAfVc-otfvRcg7pLAP36PLbCzhuzzfSed4oY2fa0g.X8o6_uUCKN9mV6o5_-Xpcpo-h_ru0EoPcZglQvyoy44g.JPEG/ISLImENYruHnXs1hlaQtc8kjX8KI.jpg?type=fb500_500"},{"title":"발끝과 월가를 동시에 점령한 크록스! 못생긴 신발로 대박 쳤다 (네이버 포스트 ─ 무신사 ─ 무신사 리포트)","contents":"<span class=\"ell\">무신사</span>","link":"https://post.naver.com/viewer/postView.naver?volumeNo=33070329&memberNo=22191262&navigationType=push","retrieved":1641374782888,"image":"https://post-phinf.pstatic.net/MjAyMjAxMDVfMjkg/MDAxNjQxMzYxMjkyODk3.RXCjtf2iVIeF4PU18XVtcqYCXmmz0mclnzASI9UQFrQg.OsNq2Qa1CHPh9dAMylq6JOBAsS4SQePZFxdnFpLQPaQg.JPEG/I_4rc4AKlGeI546t_w4L_6pwKHsg.jpg?type=fb500_500"},{"title":"어흥! 2022년을 상징하는 호랑이를 상징하는 아이템 10가지 (네이버 포스트 ─ 무신사 ─ 무신사 리포트)","contents":"<span class=\"ell\">무신사</span>","link":"https://post.naver.com/viewer/postView.naver?volumeNo=33063388&memberNo=22191262&navigationType=push","retrieved":1641281129551,"image":"https://post-phinf.pstatic.net/MjAyMjAxMDRfMTk1/MDAxNjQxMjc0MDcyNTU2.cvR4kFh480QKG5w5183_lGh5JiSDfUyxOMRfvku5cjwg.J7Tw7xjqtiU8G0AKJYQphQb5fd4cRxD3E2vuYPp1Qdog.JPEG/I0kNguYbXf72wCCtPV97d52BgRjM.jpg?type=fb500_500"},{"title":"'스걸파 느낌' 힙한 언니 스타일 하면 배드블러드지! (네이버 포스트 ─ 무신사 ─ 무신사 리포트)","contents":"<span class=\"ell\">무신사</span>","link":"https://post.naver.com/viewer/postView.naver?volumeNo=33057162&memberNo=22191262&navigationType=push","retrieved":1641198596749,"image":"https://post-phinf.pstatic.net/MjAyMjAxMDNfMTk3/MDAxNjQxMTkxOTMxMjgx.P2gIo3mTY3PE7MtrKCQc1z3SxGvtf8rzGbJjpj8PhfEg.-HePbxrAJDTZ2LtuatjOZi2sdSLO37rURG156XCS34Eg.JPEG/IjutUojW039RIoLbshBUnHW-sBCg.jpg?type=fb500_500"},{"title":"동장군과 맞서 싸워줄 체감온도 상승 아이템 다섯 가지! (네이버 포스트 ─ 무신사 ─ 무신사 리포트)","contents":"<span class=\"ell\">무신사</span>","link":"https://post.naver.com/viewer/postView.naver?volumeNo=33043466&memberNo=22191262&navigationType=push","retrieved":1643850305618,"image":"https://post-phinf.pstatic.net/MjAyMTEyMzFfMjgy/MDAxNjQwOTE5MzczMzcz.Mo5MXokRkNGOto7eXpzlz6tH8suuhQOkHQNnb8sQIoEg.npF89QtrIzxtKFNRkbrjj0K7NSBm7Fnx0L6idWBvJFQg.PNG/IGmk3Vgk0VG_Vj8hI2x24QuNs9ts.jpg?type=fb500_500"},{"title":"겨울을 위한 파카 아이템 4가지 추천 (네이버 포스트 ─ 무신사 ─ 무신사 리포트)","contents":"<span class=\"ell\">무신사</span>","link":"https://post.naver.com/viewer/postView.naver?volumeNo=33043314&memberNo=22191262&navigationType=push","retrieved":1643850305618,"image":"https://post-phinf.pstatic.net/MjAyMTEyMzFfMTk0/MDAxNjQwOTE5MzIzMjM4.5BpRuZdI6OQWwY3Gz7QWZ5dXbRxA5tWyE0FOp7rl760g.ELOXMcrpdQlZ4zN72bUWoktzu-9PYm6GgJY9tJfIwvYg.JPEG/IX0J1CukMz97_ch5v5SumrlTF-WE.jpg?type=fb500_500"},{"title":"패션의 기본 #4, 다운 재킷의 모든 것 6편 '다운 재킷 스타일링' (네이버 포스트 ─ 무신사 ─ 무신사 리포트)","contents":"<span class=\"ell\">무신사</span>","link":"https://post.naver.com/viewer/postView.naver?volumeNo=33042336&memberNo=22191262&navigationType=push","retrieved":1643850305622,"image":"https://post-phinf.pstatic.net/MjAyMTEyMzFfMzEg/MDAxNjQwOTEyMzU4NDYx.7lAJpvFFWDDThheH0_03jB4Yvot8A3xn7gR0h8NOUVkg.7qRyT5FT-GqyFy5vJT5vryE2tTcPDzrZvfaz6IE2yhog.JPEG/IX05N1avmapxhSZ9wLopVqthER8Y.jpg?type=fb500_500"},{"title":"패션의 기본 #4, 다운 재킷의 모든 것 5편 '패딩 관리 및 보관 방법 ' (네이버 포스트 ─ 무신사 ─ 무신사 리포트)","contents":"<span class=\"ell\">무신사</span>","link":"https://post.naver.com/viewer/postView.naver?volumeNo=33038459&memberNo=22191262&navigationType=push","retrieved":1645435551537,"image":"https://post-phinf.pstatic.net/MjAyMTEyMzBfNjQg/MDAxNjQwODQ1NzY1NDg4._TahItlX9TDz8n0Pmv3eE8ha1igZmycb6CQcAKzu7ucg.xHPZwov8xtTfjsaU7beS6fHP7OVkp1gkuyKvyzTnUIUg.JPEG/IccYK69_PlVlpwWTdjqbmjq_EQHs.jpg?type=fb500_500"},{"title":"인플루언서 원픽 스니커즈! \n오트리 메달리스트 신상품 발매 (네이버 포스트 ─ 무신사 ─ 무신사 리포트)","contents":"<span class=\"ell\">무신사</span>","link":"https://post.naver.com/viewer/postView.naver?volumeNo=33030123&memberNo=22191262&navigationType=push","retrieved":1649841673203,"image":"https://post-phinf.pstatic.net/MjAyMTEyMjlfMTY3/MDAxNjQwNzQ2NDgzMTM5.bDZRE7vVlC3IwPgsUTnW3RygH-34XdQIEC4QV-Fg7Nkg.GEz3INPqcw-lT1lkbsiW4bePVrIPCz9VeUQhScSGpqwg.JPEG/I6x3jcc5JPpOUCF4co_FmPWf4l-g.jpg?type=fb500_500"},{"title":"패션의 기본 #4, 다운 재킷의 모든 것 4편 '기능(FUNCTION)' (네이버 포스트 ─ 무신사 ─ 무신사 리포트)","contents":"<span class=\"ell\">무신사</span>","link":"https://post.naver.com/viewer/postView.naver?volumeNo=33024420&memberNo=22191262&navigationType=push","retrieved":1649841673204,"image":"https://post-phinf.pstatic.net/MjAyMTEyMjhfMjU0/MDAxNjQwNjY5NzA4NTk3.ApQtIIwb9tE81KGHrxxyeuPBu1b2mwdrhWqmgOcjfkwg.oJuYZLPKtGGLV8fnCLUB-3spOP0QHTOUZQh4wEjYH4wg.JPEG/IIb0AoZv7SNarye4sv6ZO0Rfl2uM.jpg?type=fb500_500"},{"title":"2022년을 물들일 올해의 컬러! 통통 튀는 매력의 퍼플 컬러 스타일링을 제안한다 (네이버 포스트 ─ 무신사 ─ 스타일 팩토리)","contents":"<span class=\"ell\">무신사</span>","link":"https://post.naver.com/viewer/postView.naver?volumeNo=33111497&memberNo=22191262&navigationType=push","retrieved":1641979557963,"image":"https://post-phinf.pstatic.net/MjAyMjAxMTJfMTM3/MDAxNjQxOTY3NTEyNjc1.VW3RBbT9FxZZEtGxUyTu0T526481XSox_w8x707-g8og.dN0rDbDq6C4skQCAiy9XL1A3YQ4DobYYHgiq7sn9_8Mg.JPEG/I8klceeA3WXyECEHIEryIkUnmTVE.jpg?type=fb500_500"},{"title":"크리틱과 힙하게 즐기는 그래픽 아이템 코디 (네이버 포스트 ─ 무신사 ─ 스타일 팩토리)","contents":"<span class=\"ell\">무신사</span>","link":"https://post.naver.com/viewer/postView.naver?volumeNo=32815130&memberNo=22191262&navigationType=push","retrieved":1637731476833,"image":"https://post-phinf.pstatic.net/MjAyMTExMjRfNDcg/MDAxNjM3NzIwNDM0Mjc5.Ibb85K2kqUzGLGylzgp-EE2LZ7NrIFTxdLxOrGo2P0Ig.94AJ2EtSY5bbUgO4yA9Q1ORdqrLgOtFm3FBDouIatL8g.JPEG/IVFvPM8GLEEit6ngSrtTYjh0mnpE.jpg?type=fb500_500"},{"title":"캐주얼부터 댄디까지, 다양한 스타일링이 가능한 커버낫 아이템 (네이버 포스트 ─ 무신사 ─ 스타일 팩토리)","contents":"<span class=\"ell\">무신사</span>","link":"https://post.naver.com/viewer/postView.naver?volumeNo=32780302&memberNo=22191262&navigationType=push","retrieved":1637224310392,"image":"https://post-phinf.pstatic.net/MjAyMTExMThfMjM1/MDAxNjM3MjE5ODU3NDQ5.VXSt9YAQ1dPHhN-24f_Anf31x80tD98kJqN6Uhsw0K4g.3cJGadQwNfq5-5ENCFhdjPES1KRiPYtvbmkBXELalfMg.JPEG/IE1ZUiZO7xGBMesIj_8k_Xd5RcN0.jpg?type=fb500_500"},{"title":"겨울 필수 아이템 ‘알파 인더스트리’의 모든 것 (네이버 포스트 ─ 무신사 ─ 스타일 팩토리)","contents":"<span class=\"ell\">무신사</span>","link":"https://post.naver.com/viewer/postView.naver?volumeNo=32733964&memberNo=22191262&navigationType=push","retrieved":1636890058919,"image":"https://post-phinf.pstatic.net/MjAyMTExMTFfMjY2/MDAxNjM2NjE1NTczNTEw.KraBGuvD-6-k3xpaxUu_i8yBfQHvOmB2bHOaab9eQigg.9FesDjKeCbvXcOGEIKSUdb0uf_ojpsQmwG5CxKlhBkgg.JPEG/ImQMtdT-ODnZA1ahKYyMS8OyZnJU.jpg?type=fb500_500"},{"title":"오늘부터 나도 셀럽! 자신을 사랑하고 표현하는 가장 올바른 방법 (네이버 포스트 ─ 무신사 ─ 스타일 팩토리)","contents":"<span class=\"ell\">무신사</span>","link":"https://post.naver.com/viewer/postView.naver?volumeNo=32687194&memberNo=22191262&navigationType=push","retrieved":1636890058920,"image":"https://post-phinf.pstatic.net/MjAyMTExMDRfMjEz/MDAxNjM2MDA1MTMxOTgz.B7xjayMG9ddRTZg_WPatalef785z7pQP4Ga2KpLSBLgg.mUpr7u-EFg6Tnljay2EooUMi4nBJJfY57YzYplu8bv8g.JPEG/IULd4ekBR-M3noo8Uc-pdKD5y-YE.jpg?type=fb500_500"},{"title":"가성비 갑! 무탠다드 코트로 겨울나기 코디법 (네이버 포스트 ─ 무신사 ─ 스타일 팩토리)","contents":"<span class=\"ell\">무신사</span>","link":"https://post.naver.com/viewer/postView.naver?volumeNo=32640298&memberNo=22191262&navigationType=push","retrieved":1635403901163,"image":"https://post-phinf.pstatic.net/MjAyMTEwMjhfMTg3/MDAxNjM1MzgyNDI2MzI2.hcFBQkwWIL7tAXfaSNVFjPH7im30rweVYwpU7ZJtopAg.ZhReahSIKxZq5aQjHEV5wj5gM84Dbgx9osU6yS-7Azkg.JPEG/IXhzsReI3R7Kt83u5elNI7EGPpKc.jpg?type=fb500_500"},{"title":"F/W 시즌 아이템 맛집은 트래블! (네이버 포스트 ─ 무신사 ─ 스타일 팩토리)","contents":"<span class=\"ell\">무신사</span>","link":"https://post.naver.com/viewer/postView.naver?volumeNo=32604273&memberNo=22191262&navigationType=push","retrieved":1634885455043,"image":"https://post-phinf.pstatic.net/MjAyMTEwMjJfNDUg/MDAxNjM0ODgyNTY0NDYy.Eymo17druSlR7x-TEVuj5-9U3974aX83u2-YWkCf5vsg.VXhgsj8ZD9XsBOY-KSWbqKzNvtIayPl4NfoTA-NMi8Qg.JPEG/IeTu0r107yZM6w2jcBuwoOzDrdq0.jpg?type=fb500_500"},{"title":"커버낫의 21 F/W 컬렉션 키 아이템으로 완성한 12가지 캐주얼 룩 (네이버 포스트 ─ 무신사 ─ 스타일 팩토리)","contents":"<span class=\"ell\">무신사</span>","link":"https://post.naver.com/viewer/postView.naver?volumeNo=32542415&memberNo=22191262&navigationType=push","retrieved":1634110891489,"image":"https://post-phinf.pstatic.net/MjAyMTEwMTNfMTIy/MDAxNjM0MTA1NzczMzU2.Wp-dhSV_n4z62Ml9XSShy3heU97QCSXfdrMEYvMtGRMg.LPzZqh2K8GYZIjNQlx-gK7DU1DWYCXg2nqTcTJzy-xYg.JPEG/ILqIE-a-EqlqSRxHi8p3y-Zk11ug.jpg?type=fb500_500"},{"title":"21 F/W 시즌을 섭렵할 그라미치 팬츠 코디네이션 (네이버 포스트 ─ 무신사 ─ 스타일 팩토리)","contents":"<span class=\"ell\">무신사</span>","link":"https://post.naver.com/viewer/postView.naver?volumeNo=32463298&memberNo=22191262&navigationType=push","retrieved":1633611915527,"image":"https://post-phinf.pstatic.net/MjAyMTA5MzBfMTUy/MDAxNjMyOTcwMjQzMzUz.ADPG5LB0b8oXWLFS4NCeu0o3Lb6wUOPMzT1JKcGhbL0g.XqiiT7R3MCw3QvRiIvRnrxztmqAZhI_Oj3bXkdkCk3Yg.JPEG/I9vL3PdPE-qNUqoSf3i4mGZ79BhU.jpg?type=fb500_500"},{"title":"올 시즌을 책임질 라퍼지스토어의 12가지 스타일링 (네이버 포스트 ─ 무신사 ─ 스타일 팩토리)","contents":"<span class=\"ell\">무신사</span>","link":"https://post.naver.com/viewer/postView.naver?volumeNo=32418032&memberNo=22191262&navigationType=push","retrieved":1633611915527,"image":"https://post-phinf.pstatic.net/MjAyMTA5MjNfNDEg/MDAxNjMyMzc2Njg1NzMx.hzfJ1x97cgQempx7MW4pmoICgePA-wK5yEH3PDHHrKAg.eLfiFO2NVkQgeCotwuGXnStBDfSWKnMYkWq3XgLg8A8g.JPEG/IpAo8TsPazzU--MESRoP2zA1on_c.jpg?type=fb500_500"},{"title":"골라 입는 재미가 가득한 멜란지 마스터의 스웨트 셋업 코디 (네이버 포스트 ─ 무신사 ─ 스타일 팩토리)","contents":"<span class=\"ell\">무신사</span>","link":"https://post.naver.com/viewer/postView.naver?volumeNo=32382948&memberNo=22191262&navigationType=push","retrieved":1633611915528,"image":"https://post-phinf.pstatic.net/MjAyMTA5MTZfMTY5/MDAxNjMxNzYyNDQxNjU2.Y5991ax-ARY16AdaX8IY7GI3ZrzJvGfTGcpcfClgD4Qg.f5hlXRlTl3iONfLBmxDu49gdGrUdBauLHU7AKiZKME8g.JPEG/IqaTpvNfLtI5uPs8Pnl4HI2CQ-9I.jpg?type=fb500_500"},{"title":"올가을, 취향 저격 환절기 아우터 코디를 낱낱이 살펴보자. (네이버 포스트 ─ 무신사 ─ 스타일 팩토리)","contents":"<span class=\"ell\">무신사</span>","link":"https://post.naver.com/viewer/postView.naver?volumeNo=32335363&memberNo=22191262&navigationType=push","retrieved":1633611915529,"image":"https://post-phinf.pstatic.net/MjAyMTA5MDlfMjk5/MDAxNjMxMTU0MzY4Mjgz.ubeFJPS__Qtwhd9JHikB11nyXUj0cyJro_BCYgsJBMgg.6C1cdKw58hEjygWj-nsUHSLiWLDpKbCS9n7EnstbfMgg.JPEG/ICggtLQHF3sZ8P633a4luy-uLN_o.jpg?type=fb500_500"},{"title":"올가을 최애템, 스웨트셔츠로 완성한 12가지 스타일링 (네이버 포스트 ─ 무신사 ─ 스타일 팩토리)","contents":"<span class=\"ell\">무신사</span>","link":"https://post.naver.com/viewer/postView.naver?volumeNo=32290125&memberNo=22191262&navigationType=push","retrieved":1633611915530,"image":"https://post-phinf.pstatic.net/MjAyMTA5MDJfMTQy/MDAxNjMwNTYxMDQyMTk1.qF3rGxd8DiO1xMboUvHt3A33zGmGPKqeoXkq-u1RR_Ig.O2lqLkgbYi7HIPUwGd8o2rMq9ed86ma2QBQPBoJ9pt8g.JPEG/ICTLXAYKg1lbH6SmVNnkx7J92KXs.jpg?type=fb500_500"},{"title":"백팩 하면 잔스포츠, 잔스포츠 하면 백팩! (네이버 포스트 ─ 무신사 ─ 스타일 팩토리)","contents":"<span class=\"ell\">무신사</span>","link":"https://post.naver.com/viewer/postView.naver?volumeNo=32243456&memberNo=22191262&navigationType=push","retrieved":1633611915531,"image":"https://post-phinf.pstatic.net/MjAyMTA4MjZfMjU2/MDAxNjI5OTQ1NTE0NTIx.aK4HTg7r6HPGqQFGWFRjFEIKHCDcfzDm9cniAT1zb-og.T5JE3a3mrJa87OEONYLx5I6Z2ztT69gd_8NSEgPZEmgg.JPEG/IzLbzrQMJAavQAXfPOY5hU0o8zjE.jpg?type=fb500_500"},{"title":"무탠다드에서 찾은 인생 데님 팬츠 (네이버 포스트 ─ 무신사 ─ 스타일 팩토리)","contents":"<span class=\"ell\">무신사</span>","link":"https://post.naver.com/viewer/postView.naver?volumeNo=32199536&memberNo=22191262&navigationType=push","retrieved":1633611915532,"image":"https://post-phinf.pstatic.net/MjAyMTA4MTlfNTUg/MDAxNjI5MzUzNTIwNTUy.WRoQqxR3tvz4SLK6fL0S-qneEmdjLla3fvFJPccDBT4g.wCyLvznitoxeu2Ka9wqYbYWKb_9CYUgjplS9-OV-DTwg.JPEG/IpoEaflHm6d2UkUQLVRD36NyajaU.jpg?type=fb500_500"},{"title":"올여름 트렌드는 단연 시티보이 룩이지! (네이버 포스트 ─ 무신사 ─ 스타일 팩토리)","contents":"<span class=\"ell\">무신사</span>","link":"https://post.naver.com/viewer/postView.naver?volumeNo=32157732&memberNo=22191262&navigationType=push","retrieved":1633611915533,"image":"https://post-phinf.pstatic.net/MjAyMTA4MTJfNjEg/MDAxNjI4NzQ1OTM4NzE2.CeeBvl-FepYK4ElAXO3G5O_h5zq3wFtDXpnJnAUACzwg.7Qy2qAMVGySv0_6ivXz7hP1fNLfCqtxH3HPsU7xyL2sg.JPEG/IZv0Gmn4vd2i1WAWHHu5sLynaddo.jpg?type=fb500_500"},{"title":"남은 여름을 책임질 서머 캐주얼 룩! (네이버 포스트 ─ 무신사 ─ 스타일 팩토리)","contents":"<span class=\"ell\">무신사</span>","link":"https://post.naver.com/viewer/postView.naver?volumeNo=32113455&memberNo=22191262&navigationType=push","retrieved":1633611915534,"image":"https://post-phinf.pstatic.net/MjAyMTA4MDVfNTEg/MDAxNjI4MTQ2MzM3NDA4.I_R43dv2B1giaFfNAeiy8Pwq1avxF3Y_Aot2uf5VEeMg.GNSXplwz8Ty9S9Qu2V-MSJJGJCNeprDhjRSGniDvQAQg.JPEG/Ifto91QGlx-QvtSYlQPbPbwPkWQI.jpg?type=fb500_500"},{"title":"휴양지가 그립다면, 이렇게 입어봐! (네이버 포스트 ─ 무신사 ─ 스타일 팩토리)","contents":"<span class=\"ell\">무신사</span>","link":"https://post.naver.com/viewer/postView.naver?volumeNo=32022498&memberNo=22191262&navigationType=push","retrieved":1633611915536,"image":"https://post-phinf.pstatic.net/MjAyMTA3MjJfMTEg/MDAxNjI2OTM3NjI0Njgw.AZWJNGHS1mXYYDhpDYshDx6zA95d97alAKhCJjyxv0gg.Yb1lQSniJi0knU9IrIjf0UVqZ_Na6RDa2oMROkuLVe8g.JPEG/I3rPercEFi6A4d0MTR0JoDeGQlvo.jpg?type=fb500_500"},{"title":"브랜디드와 함께 데님 팬츠 정복하기! (네이버 포스트 ─ 무신사 ─ 스타일 팩토리)","contents":"<span class=\"ell\">무신사</span>","link":"https://post.naver.com/viewer/postView.naver?volumeNo=31966462&memberNo=22191262&navigationType=push","retrieved":1633611915537,"image":"https://post-phinf.pstatic.net/MjAyMTA3MTRfMjkg/MDAxNjI2MjQxNzM3NjEx.iT2DXVpm16XE6xdEooJR9EA2oiiIBkbifCnE-rMTaRgg.gpyTOXxJx0caz8ZLOkF8dFhZQu_pxn9Dz14nRfF_4nAg.JPEG/Ibic-t7y68kMcg5daHGWcyVynd4Q.jpg?type=fb500_500"},{"title":"내 마음속으로 홀인원, ‘제이미웨스트’ 골프웨어 코디! (네이버 포스트 ─ 무신사 ─ 스타일 팩토리)","contents":"<span class=\"ell\">무신사</span>","link":"https://post.naver.com/viewer/postView.naver?volumeNo=31873149&memberNo=22191262&navigationType=push","retrieved":1633611915538,"image":"https://post-phinf.pstatic.net/MjAyMTA2MzBfOTcg/MDAxNjI1MDMzOTc2NTg2.uibQQMFbVUXPaG8i-eatwemQPhghCdgoTkDJZ7mXT9Ug.5o2sYHbLrcIu5oJxYyKGPe0ZCnhoQkbsA-GVROD8ZZQg.JPEG/IDoxSGX0TPNASqFZNujnbAe5bgg8.jpg?type=fb500_500"},{"title":"니트 코디 연인끼리 함께 입기 좋은 라퍼지스토어의 니트 아이템! (네이버 포스트 ─ 무신사 ─ 스타일 레슨)","contents":"<span class=\"ell\">무신사</span>","link":"https://post.naver.com/viewer/postView.naver?volumeNo=33192101&memberNo=22191262&navigationType=push","retrieved":1643189140904,"image":"https://post-phinf.pstatic.net/MjAyMjAxMjZfMjgw/MDAxNjQzMTc3MjE1OTEx.QfETRfb6RZt3S9doBzUmq38ZdFvW11A4zgoSkBd7Ilwg.KH7o9EBUoTzSYFaxyAx6bV2XTsbc0ug74JJvaMdUtWcg.JPEG/IBHgPXuJyt8WG4Q8SzoCfTk3yXVA.jpg?type=fb500_500"},{"title":"발마칸 코트 스타일링 비법! 멋짐을 보장합니다. (네이버 포스트 ─ 무신사 ─ 스타일 레슨)","contents":"<span class=\"ell\">무신사</span>","link":"https://post.naver.com/viewer/postView.naver?volumeNo=33178684&memberNo=22191262&navigationType=push","retrieved":1643019986771,"image":"https://post-phinf.pstatic.net/MjAyMjAxMjRfMjM1/MDAxNjQzMDA3MTcyNDkz.XdVUWY57dD3scYhb4-v_gWrsMhnnOaXLOOsCkT0bK0cg.dv-DwAriutEwASqTUct2Wc65HS2fjexA091n3zZCGQkg.JPEG/IIWOYAJH6Oi-56IpO8LR5FF2EoeA.jpg?type=fb500_500"},{"title":"더플코트 떡볶이 코트만 잘 입어도 패션피플이 될 수 있다! (네이버 포스트 ─ 무신사 ─ 스타일 레슨)","contents":"<span class=\"ell\">무신사</span>","link":"https://post.naver.com/viewer/postView.naver?volumeNo=33178515&memberNo=22191262&navigationType=push","retrieved":1643016205304,"image":"https://post-phinf.pstatic.net/MjAyMjAxMjRfMjU3/MDAxNjQzMDA0MTc1NTg3.vumSJ9dLCyzkODeHe9ceXQPLuvrbWBuKzLLBtxRLDTQg.3pWAnGq72uF-wcK-XV0_XW_7wboAKkpZcCvVaNoC_zYg.JPEG/IoHmRtcDNZUhhne-eb8qtwU2d00Y.jpg?type=fb500_500"},{"title":"남친룩 그 자체! 기본에 충실한 미니멀 코디 (네이버 포스트 ─ 무신사 ─ 스타일 레슨)","contents":"<span class=\"ell\">무신사</span>","link":"https://post.naver.com/viewer/postView.naver?volumeNo=33151084&memberNo=22191262&navigationType=push","retrieved":1642576828387,"image":"https://post-phinf.pstatic.net/MjAyMjAxMTlfMTMg/MDAxNjQyNTY3OTY1MTM5.yjzJPnPPAsE21qRZ7th70oQHuhEAsD0CLKsOCe0DqSQg.F4Z63CrDb4tbj83qaFa7ijCq9ZAFnra2GaedcwAs610g.JPEG/Io7S2EJtObN1I8EkEjG0hMVid9PY.jpg?type=fb500_500"},{"title":"베리페리 올해의 컬러 아이템! 이렇게 입어줘 (네이버 포스트 ─ 무신사 ─ 스타일 레슨)","contents":"<span class=\"ell\">무신사</span>","link":"https://post.naver.com/viewer/postView.naver?volumeNo=33142844&memberNo=22191262&navigationType=push","retrieved":1642480356265,"image":"https://post-phinf.pstatic.net/MjAyMjAxMThfMjk2/MDAxNjQyNDY5NjI5MTQy.lHj8cfV33R8tcgNwX9efP6IQYubeOqoD6Kv0xfztdTMg.V189AR6mvHd4v2K_QNHsyc3Vgocnx8x6ryq7AntYfhkg.JPEG/I00UA74AHGYk_nBq26s9ZfGIppfY.jpg?type=fb500_500"},{"title":"패딩 아이템으로 무장해야 할 때! 패딩과 함께한 7가지 데일리 코디 (네이버 포스트 ─ 무신사 ─ 스타일 레슨)","contents":"<span class=\"ell\">무신사</span>","link":"https://post.naver.com/viewer/postView.naver?volumeNo=33124799&memberNo=22191262&navigationType=push","retrieved":1642145101610,"image":"https://post-phinf.pstatic.net/MjAyMjAxMTRfMTc5/MDAxNjQyMTMwNTM0NjA1.HpYihwVc3FJ5blG1B5F1rK9b1GwaaRD8UoajbTUQXm4g.VoWx02DKq0nu0xFBQRE-ULoVPVdtROaqh4LiPQm3TPMg.JPEG/IPiQEd224rDP5kU6zEUOAUw33DWU.jpg?type=fb500_500"},{"title":"겨울 코디의 완성은 아우터에서 결정된다! (네이버 포스트 ─ 무신사 ─ 스타일 레슨)","contents":"<span class=\"ell\">무신사</span>","link":"https://post.naver.com/viewer/postView.naver?volumeNo=33098298&memberNo=22191262&navigationType=push","retrieved":1641803442460,"image":"https://post-phinf.pstatic.net/MjAyMjAxMTBfMTgw/MDAxNjQxNzk4MzMxNzA0.3MZAcw65uvjHaA0Ib8ZH0u4dYC1Wd6huGL-iHvIncRsg.D0nbkRn6kaLQrwswUXh7Uoyf6XpcHF9YTZ0O92lonDQg.JPEG/Ik2V8oPFX4CCXYRVgJxfPoVVlrE8.jpg?type=fb500_500"},{"title":"2022년을 지배할 컬러, 베리 페리 (네이버 포스트 ─ 무신사 ─ 스타일 레슨)","contents":"<span class=\"ell\">무신사</span>","link":"https://post.naver.com/viewer/postView.naver?volumeNo=33082994&memberNo=22191262&navigationType=push","retrieved":1641533132790,"image":"https://post-phinf.pstatic.net/MjAyMjAxMDdfNzkg/MDAxNjQxNTIzMDAxMTQ5.TixtEoVEzhuiFZzkI__qUqO3TpbrC-RdJ7xH-t-ZNsog.CPMD2xb0Vl7JQH2Cg_OVBus0zPiHmfDMiWyrM-mYX9cg.JPEG/ISNAtwMB-qAxoanvIe8kIir6XbVQ.jpg?type=fb500_500"},{"title":"리프로덕션 오브 파운드 21 F/W 신상품 한정 발매 (네이버 포스트 ─ 무신사 ─ 스타일 레슨)","contents":"<span class=\"ell\">무신사</span>","link":"https://post.naver.com/viewer/postView.naver?volumeNo=32786181&memberNo=22191262&navigationType=push","retrieved":1637389637575,"image":"https://post-phinf.pstatic.net/MjAyMTExMTlfMTM0/MDAxNjM3MjkxNDg5OTY5.eToyyB2Sq7887YL_380M9thDkoyrW4GNp8LRXNCdL38g.EQqhyngf7flYO5BAm5zf8zZ6NG27ScsijeT412C4TZ4g.JPEG/IArrVmHyFxW5NomoEumWE4CnYb98.jpg?type=fb500_500"},{"title":"숏 패딩으로 본격적인 겨울 준비하기! (네이버 포스트 ─ 무신사 ─ 스타일 레슨)","contents":"<span class=\"ell\">무신사</span>","link":"https://post.naver.com/viewer/postView.naver?volumeNo=32763695&memberNo=22191262&navigationType=push","retrieved":1637051311032,"image":"https://post-phinf.pstatic.net/MjAyMTExMTZfMTI4/MDAxNjM3MDQxOTEyMjg4.bVf1QsBqE3mfaTbmrHhFCOI8bBkufrPNCe6NJXgl43wg.KactgTTsHLjp_iYc73OlZ6E0k5FbAt-cu7nv1E5qTzsg.JPEG/IlrMmIM1GavcXXuuT6C-2AOVJtFA.jpg?type=fb500_500"},{"title":"평범하게 특별하다! 무신사 스탠다드 맨즈 컬렉션 (네이버 포스트 ─ 무신사 ─ 스타일 레슨)","contents":"<span class=\"ell\">무신사</span>","link":"https://post.naver.com/viewer/postView.naver?volumeNo=32717530&memberNo=22191262&navigationType=push","retrieved":1636890062960,"image":"https://post-phinf.pstatic.net/MjAyMTExMDlfMjQg/MDAxNjM2NDM5MjM5NjM0.YzVcNHaXuAyhUYkQYkY21Isv226SCNjt6gmRrzQfX78g.KR9Njqp9TiZ9GchoxPKozmQrdk4RCYDroykAxPoBDKgg.JPEG/InN2bPPUMyUBEQ_-eJlg7fwbZT9g.jpg?type=fb500_500"},{"title":"대세 배우 구교환의 최애 패션 스타일 10 (네이버 포스트 ─ 무신사 ─ 스타일 레슨)","contents":"<span class=\"ell\">무신사</span>","link":"https://post.naver.com/viewer/postView.naver?volumeNo=32604507&memberNo=22191262&navigationType=push","retrieved":1634888464850,"image":"https://post-phinf.pstatic.net/MjAyMTEwMjJfMjEg/MDAxNjM0ODgyMDkwMjAz.IMbWdKvjTP4CRXII8QFEDZcoB--4y4cMO3buweLI3yYg.ZSdYLqyutOQJJnMb3PiE92ldV5-W8FwLxZvK6CISEoAg.JPEG/Isb-Zmp61y0EUJs5OZWZPh5AxVuY.jpg?type=fb500_500"},{"title":"무신사의 뮤즈 유아인의 감성 담은 #SELF_LOVE 캠페인 화보! (네이버 포스트 ─ 무신사 ─ 스타일 레슨)","contents":"<span class=\"ell\">무신사</span>","link":"https://post.naver.com/viewer/postView.naver?volumeNo=32581191&memberNo=22191262&navigationType=push","retrieved":1634626285496,"image":"https://post-phinf.pstatic.net/MjAyMTEwMTlfMTEg/MDAxNjM0NjIwNTMwNjA2.oMytrUnPQHgGhSLWupuRXlBAp5QZO_PanrYYOumPyC0g.ESE739ZL6GJ9-ViP5WErR1Iqmmdkj_Jd__iqBqhjmtMg.JPEG/IaAWL7BcdTg3MouQesYsV0FMLA_M.jpg?type=fb500_500"},{"title":"6가지 코디로 알아보는 그라미치 21 F/W 컬렉션 (네이버 포스트 ─ 무신사 ─ 스타일 레슨)","contents":"<span class=\"ell\">무신사</span>","link":"https://post.naver.com/viewer/postView.naver?volumeNo=32320129&memberNo=22191262&navigationType=push","retrieved":1633611919274,"image":"https://post-phinf.pstatic.net/MjAyMTA5MDdfNCAg/MDAxNjMwOTgyMzI4ODQw.YP_tvnBifijXHhOOOaFrBb9kyhxCgUW2DNPBTGTh0Wcg.mG9PJYTyKZ5Pqp-A4c3WFH7SzcCoTlt-snnhjmw0dT4g.JPEG/IXBP3TYdTJgiojqBynibIe-AMbEc.jpg?type=fb500_500"},{"title":"데님 아이템으로 완성한 12가지 환절기 데일리 룩 (네이버 포스트 ─ 무신사 ─ 스타일 레슨)","contents":"<span class=\"ell\">무신사</span>","link":"https://post.naver.com/viewer/postView.naver?volumeNo=32273821&memberNo=22191262&navigationType=push","retrieved":1633611919275,"image":"https://post-phinf.pstatic.net/MjAyMTA4MzFfMTcg/MDAxNjMwMzg1MjM0NTM0.B9jVf3SrWx-lc9s9ppxbM3Wg4xdFl_tIZZ0OG5a4M4sg.Dr6stNha-gFceI-3vbDZk9Y0ZuAWvJ7fb5kihZHM7jYg.JPEG/ImEFlrYYLBR2Vpgq4KBFIfUj3XZo.jpg?type=fb500_500"},{"title":"찌는 듯한 더위를 시원하게 식혀줄 린넨 코디 7 (네이버 포스트 ─ 무신사 ─ 스타일 레슨)","contents":"<span class=\"ell\">무신사</span>","link":"https://post.naver.com/viewer/postView.naver?volumeNo=32142891&memberNo=22191262&navigationType=push","retrieved":1633611919276,"image":"https://post-phinf.pstatic.net/MjAyMTA4MTBfMTg2/MDAxNjI4NTczOTI5ODQ2.7ugPbRcNKi_qIlclMuc7K7ZD9f3uuSSxagPvC6EaPT8g.lm74I92ygWGjU57RQTl9-IiFlhJhPu6CFEd9GDMHxSUg.JPEG/I7B6HdB_0XiDGtMLRd3iXE1amm3g.jpg?type=fb500_500"},{"title":"멜란지 마스터의 컬러 티셔츠로 매일 색다르게! (네이버 포스트 ─ 무신사 ─ 스타일 레슨)","contents":"<span class=\"ell\">무신사</span>","link":"https://post.naver.com/viewer/postView.naver?volumeNo=32068848&memberNo=22191262&navigationType=push","retrieved":1633611919277,"image":"https://post-phinf.pstatic.net/MjAyMTA3MjlfODIg/MDAxNjI3NTQ0NjkwNTIx.LTtymh7HvcB_u9EanNxpZJhsRgb7ezSYM2fEQhDGnLYg.aPTFqRnuwbCPthTUWA2V_Quf8sdsCIuCc35CG1BgPpAg.JPEG/IVqbwqFc6e6vKetAHTcuQ2YKRp74.jpg?type=fb500_500"},{"title":"여름 코디가 막막할 땐 무신사 스탠다드가 정답! (네이버 포스트 ─ 무신사 ─ 스타일 레슨)","contents":"<span class=\"ell\">무신사</span>","link":"https://post.naver.com/viewer/postView.naver?volumeNo=32005246&memberNo=22191262&navigationType=push","retrieved":1645435559352,"image":"https://post-phinf.pstatic.net/MjAyMTA3MjBfMTk5/MDAxNjI2NzU5MTUzMzM0.PrdWORp57Hg9gsssgCi1mhPRecGAroK1lmBBsBA9LFcg.Nkl3ERT3Kn9i15eS3xGGPP-_VjtU0r1I-zWp_ZFWeI0g.JPEG/ImV6DcZDurTh0aSnVpl95zOHz-Ac.jpg?type=fb500_500"},{"title":"무탠다드 티셔츠 하나면 만사 오케이! (네이버 포스트 ─ 무신사 ─ 스타일 레슨)","contents":"<span class=\"ell\">무신사</span>","link":"https://post.naver.com/viewer/postView.naver?volumeNo=31955591&memberNo=22191262&navigationType=push","retrieved":1645435559352,"image":"https://post-phinf.pstatic.net/MjAyMTA3MTNfMjUy/MDAxNjI2MTM4NTI1MDIy.yol3NClVpTaOFceVL9YuZwAtrU4sayHxwQcKV0NkZ8Ig.P5m5YMGW9cAkmjAHHjWWL-fi8OpgipglydJzWMp2cX0g.JPEG/IuEgiPLPv8zaBD-TXoeJk4JqG1LU.jpg?type=fb500_500"},{"title":"트렌디하게 입는 와이드 팬츠 코디 4 (네이버 포스트 ─ 무신사 ─ 스타일 레슨)","contents":"<span class=\"ell\">무신사</span>","link":"https://post.naver.com/viewer/postView.naver?volumeNo=31333131&memberNo=22191262&navigationType=push","retrieved":1645435559353,"image":"https://post-phinf.pstatic.net/MjAyMTA0MjJfMTk1/MDAxNjE5MDYwOTMxMzM1.DrE5-vCKK9xNboyfqI-dHMfwO-VhBiy_zMal2x8dDkog.DC8ucmCyyaFVAkUsqHgeQ0k0v186Gglpnyif_bji5Hwg.JPEG/IBHX__51yowwOZTx2OH-74eP0X2Q.jpg?type=fb500_500"},{"title":"재입고와 동시에 1위, 반스 컴피쿠시 원! (네이버 포스트 ─ 무신사 ─ 무신사 스토어 랭킹)","contents":"<span class=\"ell\">무신사</span>","link":"https://post.naver.com/viewer/postView.naver?volumeNo=32119004&memberNo=22191262&navigationType=push","retrieved":1633611923022,"image":"https://post-phinf.pstatic.net/MjAyMTA4MDZfMTk3/MDAxNjI4MjIwOTA1MDAw.GlAO-tyrSZbtyERNKuVrAnlRx-HoXIJN7alaOCHBaSgg._lAszK5LMtejgmGWWi8LofUoa69ohCX2IM4lMckR8bkg.JPEG/IhJhEVk6I9kMfmgcmGWH8duwBL-4.jpg?type=fb500_500"},{"title":"지금 가장 핫한 아이템, 폴로 랄프 로렌 셔츠! (네이버 포스트 ─ 무신사 ─ 무신사 스토어 랭킹)","contents":"<span class=\"ell\">무신사</span>","link":"https://post.naver.com/viewer/postView.naver?volumeNo=32073568&memberNo=22191262&navigationType=push","retrieved":1633611923024,"image":"https://post-phinf.pstatic.net/MjAyMTA3MzBfODYg/MDAxNjI3NjEwMjkyNDIw.ZjWEg5Vx074xcIp7tgw-FFwBZ8jQqVlyDNpvwbd_uuUg.rzbmeQQPW4rh4oKZgRstCWLVjgUKV85_Q9kCTM35a14g.JPEG/IpSm9d23YklQXvltSii_c4GFmIcE.jpg?type=fb500_500"},{"title":"폭발적인 인기! \n뉴발란스 × 토앤토 리커버리 슈즈 (네이버 포스트 ─ 무신사 ─ 무신사 스토어 랭킹)","contents":"<span class=\"ell\">무신사</span>","link":"https://post.naver.com/viewer/postView.naver?volumeNo=32059825&memberNo=22191262&navigationType=push","retrieved":1633611923024,"image":"https://post-phinf.pstatic.net/MjAyMTA3MjhfMTY4/MDAxNjI3NDUxMzI3MTk0.ngn0bRvC3ItUMEgGRCQpegglkxj31LA3yEBu6dBta-cg.4wGhcrYV7_0rhEUMF45YGg_6uCQ3Z21nWUFmlkrHxvIg.JPEG/IlBBWcDJgoec_rfPsZ7KO4lKfN2s.jpg?type=fb500_500"},{"title":"대세가 된  피지컬 에듀케이션 디파트먼트의 티셔츠 (네이버 포스트 ─ 무신사 ─ 무신사 스토어 랭킹)","contents":"<span class=\"ell\">무신사</span>","link":"https://post.naver.com/viewer/postView.naver?volumeNo=32042444&memberNo=22191262&navigationType=push","retrieved":1633611923025,"image":"https://post-phinf.pstatic.net/MjAyMTA3MjZfNTEg/MDAxNjI3MjY3ODI5NjQy.1o2UH-q4-BvOIspdVGFjuTwcnpdvAF4-XrGJzk6CrrAg.jLbazfQ4Asdp_PYAj150EjHbW-TxKbzJOwdmFoEBkGgg.JPEG/ItpPc2d75rh3anC7XiPKmpv7GGyY.jpg?type=fb500_500"},{"title":"대세템 등극! 컨버스 런스타 하이크 (네이버 포스트 ─ 무신사 ─ 무신사 스토어 랭킹)","contents":"<span class=\"ell\">무신사</span>","link":"https://post.naver.com/viewer/postView.naver?volumeNo=32012216&memberNo=22191262&navigationType=push","retrieved":1633611923026,"image":"https://post-phinf.pstatic.net/MjAyMTA3MjFfMTU1/MDAxNjI2ODQwMjIwMDA0.KcVe22YwcRW1IIsFPgh84UD-9MZlTCxCLrVae1Isyxwg.9Hg5yqTz0m6XfE3EDx4NZ7noY0dO7Q02T13Jhz3tHn8g.JPEG/I9pQLCmLm5mUWii32vf5xCzj3wMs.jpg?type=fb500_500"},{"title":"시원하고 깔끔한 여름 코디 필수템, 피케 티셔츠 (네이버 포스트 ─ 무신사 ─ 무신사 스토어 랭킹)","contents":"<span class=\"ell\">무신사</span>","link":"https://post.naver.com/viewer/postView.naver?volumeNo=31932259&memberNo=22191262&navigationType=push","retrieved":1633611923028,"image":"https://post-phinf.pstatic.net/MjAyMTA3MDlfMTAy/MDAxNjI1NzkxMjAzMTM1.2zGsAPxlcwPsS7DP97hnAB8nYEWScnNu4xk3ShOru-Mg.uEA07mc8odUpRYfaxO4mAcwJh5jhMhBU_YhT4VxXpDwg.JPEG/IlmsamK8gpjRV1fPmgEBPmHWpC3M.jpg?type=fb500_500"},{"title":"1년 만에 돌아온 레전드, 컨버스 쿼드 패널 (네이버 포스트 ─ 무신사 ─ 무신사 스토어 랭킹)","contents":"<span class=\"ell\">무신사</span>","link":"https://post.naver.com/viewer/postView.naver?volumeNo=31916951&memberNo=22191262&navigationType=push","retrieved":1633611923029,"image":"https://post-phinf.pstatic.net/MjAyMTA3MDdfOTMg/MDAxNjI1NjIyMDA0NTQw.UgEWtgcIdM2-wmLFY4t9T4ZgmH9jEd4OAlVw_aXGtpEg.erDkm7ZYwgxpauthWe5_LofjoAfUK1ldSd8xfpltZ-Ig.JPEG/ID_OWxpWAlLHKU2uvR7ctqwd590I.jpg?type=fb500_500"},{"title":"서머 코디 대세 아이템, 스트라이프 티셔츠 (네이버 포스트 ─ 무신사 ─ 무신사 스토어 랭킹)","contents":"<span class=\"ell\">무신사</span>","link":"https://post.naver.com/viewer/postView.naver?volumeNo=31889263&memberNo=22191262&navigationType=push","retrieved":1633611923029,"image":"https://post-phinf.pstatic.net/MjAyMTA3MDJfMTA4/MDAxNjI1MjA3NjQzMDQ0.ZbnlTggoriDnQnVG-BHVDAmyh3aHzt9gcLKsWEdzqFQg.jjh-PUKBrfCmVFN7bNcDb375WPYLyH6QN7oFr-ogpVIg.JPEG/I0-nkFXMNxy_wD-V4bNE72rK-BAU.jpg?type=fb500_500"},{"title":"여름 최강 슬리퍼, 골스튜디오 그래비티밸런스 프로 (네이버 포스트 ─ 무신사 ─ 무신사 스토어 랭킹)","contents":"<span class=\"ell\">무신사</span>","link":"https://post.naver.com/viewer/postView.naver?volumeNo=31820482&memberNo=22191262&navigationType=push","retrieved":1633611923030,"image":"https://post-phinf.pstatic.net/MjAyMTA2MjNfNDUg/MDAxNjI0NDExNDkxODkz.2tpyh_hhrD8yc2SR5UrklhJ96D84KByDI98tYxvp158g.zpkjuAAMZ4_l_JSst3wkziV8LupfI2KtFf6JoL6iJ64g.JPEG/INOFUOMTCYQgo4xIA1d8e3sarlyQ.jpg?type=fb500_500"},{"title":"지금 입기 딱 좋은 인기 반팔 셔츠 10 (네이버 포스트 ─ 무신사 ─ 무신사 스토어 랭킹)","contents":"<span class=\"ell\">무신사</span>","link":"https://post.naver.com/viewer/postView.naver?volumeNo=31803994&memberNo=22191262&navigationType=push","retrieved":1633611923031,"image":"https://post-phinf.pstatic.net/MjAyMTA2MjFfMjc2/MDAxNjI0MjUyMjQ3NTA2.rY0ybj5IoFlmkCXCM9Y6vkn5msVkoC7acFbkOQRIKKUg.PKufR_K8a5BzrtSTS_g5Bq-CVJlnRjnlYlHk3KBZmRog.JPEG/IkiYqNVEUrr8Tdv7qbO40T8a0K8U.jpg?type=fb500_500"},{"title":"이번 여름 대세템, \n버뮤다 팬츠 무신사 스토어 랭킹 (네이버 포스트 ─ 무신사 ─ 무신사 스토어 랭킹)","contents":"<span class=\"ell\">무신사</span>","link":"https://post.naver.com/viewer/postView.naver?volumeNo=31550559&memberNo=22191262&navigationType=push","retrieved":1633611923031,"image":"https://post-phinf.pstatic.net/MjAyMTA1MjFfMjU3/MDAxNjIxNTc4MTc1Mzgx.mSMJr2HGNa0mbFC4hb4T9rqe-xAc6WPajC7IfuP4n1Mg.5FstvXW9C5xNSBVKwCPjIoMQZJ1XIyDz07Rk2TyiaLIg.JPEG/IOvCgF1SNURYFuqgtbOPDJAw-8z4.jpg?type=fb500_500"},{"title":"4월 2주차 트랙 팬츠 랭킹 TOP 10 (네이버 포스트 ─ 무신사 ─ 무신사 스토어 랭킹)","contents":"<span class=\"ell\">무신사</span>","link":"https://post.naver.com/viewer/postView.naver?volumeNo=31335185&memberNo=22191262&navigationType=push","retrieved":1633611923032,"image":"https://post-phinf.pstatic.net/MjAyMTA0MjNfNTUg/MDAxNjE5MTUzMzgzODcy.gR-SjGGbi3yK0u3jbAPOmwYkE2dxI_O19Y-lZfwWjrcg.IoiLHsKVqYrE6lQs9Lxkl99U4gRcUzun-QUKsRX5n1Yg.JPEG/I5xw6d9NC-JLqgpgwAaPJyz-kqN0.jpg?type=fb500_500"},{"title":"4월 2주차 스니커즈 랭킹 TOP 10 (네이버 포스트 ─ 무신사 ─ 무신사 스토어 랭킹)","contents":"<span class=\"ell\">무신사</span>","link":"https://post.naver.com/viewer/postView.naver?volumeNo=31335160&memberNo=22191262&navigationType=push","retrieved":1633611923032,"image":"https://post-phinf.pstatic.net/MjAyMTA0MjJfMjgy/MDAxNjE5MDU2NjMyMjkx.-C-XsQbay5yoTQ52PsjmVx3oTox3j7Ex47QFwr716o4g.5TlTdAWBN2qLZ3x-iHv9mpUslXlQ8PgsVR2XJlNA3Ysg.JPEG/IeGFHNwjq4Z3b7cb3CGrAWhgPloM.jpg?type=fb500_500"},{"title":"4월 2주차 무신사 주간 랭킹 TOP 10 (네이버 포스트 ─ 무신사 ─ 무신사 스토어 랭킹)","contents":"<span class=\"ell\">무신사</span>","link":"https://post.naver.com/viewer/postView.naver?volumeNo=31323781&memberNo=22191262&navigationType=push","retrieved":1633611923033,"image":"https://post-phinf.pstatic.net/MjAyMTA0MjJfMTAg/MDAxNjE5MDIxNTU1NzQy.jfOK3UlA_RInd1_VKWZOicN_mvmjAuEzlFcV3iehk1Ig.YuLG2hlhAX3ja1DxYdbQkvAgyWzIv8VzOSHxGz1xb4Qg.JPEG/IZ9qMWrhjBLuzV9y2LhuQ6YCiXzQ.jpg?type=fb500_500"},{"title":"4월 1주차 반팔 티셔츠 랭킹 TOP 10 (네이버 포스트 ─ 무신사 ─ 무신사 스토어 랭킹)","contents":"<span class=\"ell\">무신사</span>","link":"https://post.naver.com/viewer/postView.naver?volumeNo=31259688&memberNo=22191262&navigationType=push","retrieved":1633611923034,"image":"https://post-phinf.pstatic.net/MjAyMTA0MTZfOTMg/MDAxNjE4NTUwNzk0Njg3.AnwhOyTcRvcZknEKOiqcLT5_-ZiKIR6LKQT7ztA3Uj0g.rDy7s0dFONsGsxl_9XIplhuB6J1bN1FGl9_LFZeXT0Ig.JPEG/IOVJIvqSxjmTLUhXL3fDwHKyXdQ4.jpg?type=fb500_500"},{"title":"4월 1주차 피케 티셔츠 랭킹 TOP 10 (네이버 포스트 ─ 무신사 ─ 무신사 스토어 랭킹)","contents":"<span class=\"ell\">무신사</span>","link":"https://post.naver.com/viewer/postView.naver?volumeNo=31258700&memberNo=22191262&navigationType=push","retrieved":1633611923035,"image":"https://post-phinf.pstatic.net/MjAyMTA0MTVfMTEg/MDAxNjE4NDY0MTM0ODAx.xjA4ixamO1fvXVY_SncczBvT46W5vievQ6hv6K8Vlokg.iUbJhw_NvLgj0Fe3I0qQvJZBoF36fj5JnANvjrhSC3gg.JPEG/Iy-g_VbjArYlxHbMebLrQgvd5iXg.jpg?type=fb500_500"},{"title":"4월 1주차 스니커즈 랭킹 TOP 10 (네이버 포스트 ─ 무신사 ─ 무신사 스토어 랭킹)","contents":"<span class=\"ell\">무신사</span>","link":"https://post.naver.com/viewer/postView.naver?volumeNo=31258677&memberNo=22191262&navigationType=push","retrieved":1633611923036,"image":"https://post-phinf.pstatic.net/MjAyMTA0MTVfMTUw/MDAxNjE4NDYzNTE1MTI0.9QnmnlCLZTpZJdDYqTyXReTPDZb6izvIDZqpL0bzMGwg.NJfC4_roBTxGjtTHZ--Wo795qc7PZSJsojtn3I3BSGUg.JPEG/I8THoyd9jn-Ya3wEFas6DoEnNHZw.jpg?type=fb500_500"},{"title":"4월 1주차 무신사 주간 랭킹 TOP 10 (네이버 포스트 ─ 무신사 ─ 무신사 스토어 랭킹)","contents":"<span class=\"ell\">무신사</span>","link":"https://post.naver.com/viewer/postView.naver?volumeNo=31244348&memberNo=22191262&navigationType=push","retrieved":1633611923038,"image":"https://post-phinf.pstatic.net/MjAyMTA0MTNfMTQ2/MDAxNjE4Mjk0MjU5ODM5.wPj0eUCaj13FgBj4yj3vZ_TTsqdzuBMtOw8oCXErqqkg.58R671rTxknY4my1NbZBjQmRkDgyS2v50NR6sAv7Uagg.JPEG/I4vU73rlhKd3iONaV_jxyk2OhDbQ.jpg?type=fb500_500"},{"title":"3월 5주차 크로스 백 랭킹 TOP 10 (네이버 포스트 ─ 무신사 ─ 무신사 스토어 랭킹)","contents":"<span class=\"ell\">무신사</span>","link":"https://post.naver.com/viewer/postView.naver?volumeNo=31185646&memberNo=22191262&navigationType=push","retrieved":1643850317904,"image":"https://post-phinf.pstatic.net/MjAyMTA0MDlfMjE4/MDAxNjE3OTM0NjA0Njc4.TquoNIE9qPAgLaRjIf-pdprigMofMf_1B1u-A-MofeQg.dlc0gsud4A2LF00QcltKz1wKH0xv8qY4dQv9ovt5Xcgg.JPEG/IBxYyEfQy_aswAr6LC_nj5kx4jVE.jpg?type=fb500_500"},{"title":"3월 5주차 긴팔 티셔츠 랭킹 TOP 10 (네이버 포스트 ─ 무신사 ─ 무신사 스토어 랭킹)","contents":"<span class=\"ell\">무신사</span>","link":"https://post.naver.com/viewer/postView.naver?volumeNo=31185629&memberNo=22191262&navigationType=push","retrieved":1650599325460,"image":"https://post-phinf.pstatic.net/MjAyMTA0MDhfMTA4/MDAxNjE3ODQzODAyODg3.5g7O5jFC2V9JW7zqpmVHk5r2BGLE7y4ihecqmzSxBq8g.L6diL11tIGZdsJ_7Uy4swgyQF4g4eG9sBburCOr0QMgg.JPEG/Ias2ApupoJoxcGEGajiHwaM2sJKA.jpg?type=fb500_500"}]}