{"title":"무신사 ─ 브랜드 스냅","url":"https://magazine.musinsa.com/index.php?m=shopstaff&_y=2021&ordw=d_regis&p=1","favicon":"https://magazine.musinsa.com/favicon.ico","elements":[{"title":"강승환","contents":"드네이지","link":"https://magazine.musinsa.com/index.php?m=shopstaff&_y=2021&ordw=d_regis&p=1&uid=163631","retrieved":1633585226880,"image":"https://image.musinsa.com/mfile_s01/_shopstaff/250.staff_615e7d9544d03.jpg?20211007142730"},{"title":"김남영","contents":"스타터","link":"https://magazine.musinsa.com/index.php?m=shopstaff&_y=2021&ordw=d_regis&p=1&uid=163630","retrieved":1633585226881,"image":"https://image.musinsa.com/mfile_s01/_shopstaff/250.staff_615e7ccae04a2.jpg?20211007142730"},{"title":"전성수","contents":"디폴트벨류","link":"https://magazine.musinsa.com/index.php?m=shopstaff&_y=2021&ordw=d_regis&p=1&uid=163629","retrieved":1633585226881,"image":"https://image.musinsa.com/mfile_s01/_shopstaff/250.staff_615e7b6bf0e22.jpg?20211007142730"},{"title":"이주한","contents":"엠엠지엘","link":"https://magazine.musinsa.com/index.php?m=shopstaff&_y=2021&ordw=d_regis&p=1&uid=163628","retrieved":1633585226882,"image":"https://image.musinsa.com/mfile_s01/_shopstaff/250.staff_615e7a11399de.jpg?20211007142730"},{"title":"김도현","contents":"엠엠지엘","link":"https://magazine.musinsa.com/index.php?m=shopstaff&_y=2021&ordw=d_regis&p=1&uid=163627","retrieved":1633585226883,"image":"https://image.musinsa.com/mfile_s01/_shopstaff/250.staff_615e798c5ac85.jpg?20211007142730"},{"title":"신동수","contents":"엠엠지엘","link":"https://magazine.musinsa.com/index.php?m=shopstaff&_y=2021&ordw=d_regis&p=1&uid=163626","retrieved":1633585226883,"image":"https://image.musinsa.com/mfile_s01/_shopstaff/250.staff_615e795039997.jpg?20211007142730"},{"title":"성유진","contents":"골라 클래식","link":"https://magazine.musinsa.com/index.php?m=shopstaff&_y=2021&ordw=d_regis&p=1&uid=163625","retrieved":1633585226885,"image":"https://image.musinsa.com/mfile_s01/_shopstaff/250.staff_615e77fb22bc3.jpg?20211007142730"},{"title":"김지은","contents":"닐링","link":"https://magazine.musinsa.com/index.php?m=shopstaff&_y=2021&ordw=d_regis&p=1&uid=163624","retrieved":1633585226886,"image":"https://image.musinsa.com/mfile_s01/_shopstaff/250.staff_615e77dae0a2f.jpg?20211007142615"},{"title":"노선정","contents":"스타터","link":"https://magazine.musinsa.com/index.php?m=shopstaff&_y=2021&ordw=d_regis&p=1&uid=163623","retrieved":1633585226887,"image":"https://image.musinsa.com/mfile_s01/_shopstaff/250.staff_615e7840e5441.jpg?20211007142615"},{"title":"최유정","contents":"엑서사이즈","link":"https://magazine.musinsa.com/index.php?m=shopstaff&_y=2021&ordw=d_regis&p=1&uid=163622","retrieved":1633585226887,"image":"https://image.musinsa.com/mfile_s01/_shopstaff/250.staff_615e74cf203b6.jpg?20211007142615"},{"title":"최원진","contents":"엑서사이즈","link":"https://magazine.musinsa.com/index.php?m=shopstaff&_y=2021&ordw=d_regis&p=1&uid=163621","retrieved":1633585226888,"image":"https://image.musinsa.com/mfile_s01/_shopstaff/250.staff_615e72f363067.jpg?20211007142615"},{"title":"이재은","contents":"엑서사이즈","link":"https://magazine.musinsa.com/index.php?m=shopstaff&_y=2021&ordw=d_regis&p=1&uid=163620","retrieved":1633585226889,"image":"https://image.musinsa.com/mfile_s01/_shopstaff/250.staff_615e71c16667a.jpg?20211007142615"},{"title":"이학승","contents":"오가프","link":"https://magazine.musinsa.com/index.php?m=shopstaff&_y=2021&ordw=d_regis&p=1&uid=163619","retrieved":1633585226892,"image":"https://image.musinsa.com/mfile_s01/_shopstaff/250.staff_615e71b523c1e.jpg?20211007142615"},{"title":"박성호","contents":"엑서사이즈","link":"https://magazine.musinsa.com/index.php?m=shopstaff&_y=2021&ordw=d_regis&p=1&uid=163618","retrieved":1633585226892,"image":"https://image.musinsa.com/mfile_s01/_shopstaff/250.staff_615e70374a07f.jpg?20211007142615"},{"title":"고현비","contents":"엑서사이즈","link":"https://magazine.musinsa.com/index.php?m=shopstaff&_y=2021&ordw=d_regis&p=1&uid=163617","retrieved":1633585226898,"image":"https://image.musinsa.com/mfile_s01/_shopstaff/250.staff_615e6e9e2d1d9.jpg?20211007142615"},{"title":"엄건식","contents":"브릭","link":"https://magazine.musinsa.com/index.php?m=shopstaff&_y=2021&ordw=d_regis&p=1&uid=163616","retrieved":1633585226899,"image":"https://image.musinsa.com/mfile_s01/_shopstaff/250.staff_615e6d12cb818.jpg?20211007142615"},{"title":"임채일","contents":"라퍼지스토어","link":"https://magazine.musinsa.com/index.php?m=shopstaff&_y=2021&ordw=d_regis&p=1&uid=163615","retrieved":1633585226900,"image":"https://image.musinsa.com/mfile_s01/_shopstaff/250.staff_615e6c9dbe818.jpg?20211007142615"},{"title":"김진록","contents":"와일드띵스","link":"https://magazine.musinsa.com/index.php?m=shopstaff&_y=2021&ordw=d_regis&p=1&uid=163614","retrieved":1633585226901,"image":"https://image.musinsa.com/mfile_s01/_shopstaff/250.staff_615e6c9338b20.jpg?20211007142615"},{"title":"김태원","contents":"트래블","link":"https://magazine.musinsa.com/index.php?m=shopstaff&_y=2021&ordw=d_regis&p=1&uid=163613","retrieved":1633585226903,"image":"https://image.musinsa.com/mfile_s01/_shopstaff/250.staff_615e6c72e1273.jpg?20211007142615"},{"title":"이민재","contents":"라퍼지스토어","link":"https://magazine.musinsa.com/index.php?m=shopstaff&_y=2021&ordw=d_regis&p=1&uid=163612","retrieved":1633585226904,"image":"https://image.musinsa.com/mfile_s01/_shopstaff/250.staff_615e6c63546c0.jpg?20211007142615"},{"title":"송원석","contents":"라퍼지스토어","link":"https://magazine.musinsa.com/index.php?m=shopstaff&_y=2021&ordw=d_regis&p=1&uid=163611","retrieved":1633585226905,"image":"https://image.musinsa.com/mfile_s01/_shopstaff/250.staff_615e6c33d7953.jpg?20211007142615"},{"title":"김채운","contents":"트래블","link":"https://magazine.musinsa.com/index.php?m=shopstaff&_y=2021&ordw=d_regis&p=1&uid=163610","retrieved":1633585226906,"image":"https://image.musinsa.com/mfile_s01/_shopstaff/250.staff_615e6c0973ac5.jpg?20211007142615"},{"title":"조민지","contents":"와일드띵스","link":"https://magazine.musinsa.com/index.php?m=shopstaff&_y=2021&ordw=d_regis&p=1&uid=163609","retrieved":1633585226907,"image":"https://image.musinsa.com/mfile_s01/_shopstaff/250.staff_615e6bf588ab4.jpg?20211007142615"},{"title":"김진호","contents":"트래블","link":"https://magazine.musinsa.com/index.php?m=shopstaff&_y=2021&ordw=d_regis&p=1&uid=163608","retrieved":1633585226909,"image":"https://image.musinsa.com/mfile_s01/_shopstaff/250.staff_615e6bacdc56b.jpg?20211007142615"},{"title":"곽유빈","contents":"트래블","link":"https://magazine.musinsa.com/index.php?m=shopstaff&_y=2021&ordw=d_regis&p=1&uid=163607","retrieved":1633585226910,"image":"https://image.musinsa.com/mfile_s01/_shopstaff/250.staff_615e6b64bc88e.jpg?20211007142615"},{"title":"오상윤","contents":"와일드띵스","link":"https://magazine.musinsa.com/index.php?m=shopstaff&_y=2021&ordw=d_regis&p=1&uid=163606","retrieved":1633585226911,"image":"https://image.musinsa.com/mfile_s01/_shopstaff/250.staff_615e6b438603b.jpg?20211007142615"},{"title":"고현비","contents":"트래블","link":"https://magazine.musinsa.com/index.php?m=shopstaff&_y=2021&ordw=d_regis&p=1&uid=163605","retrieved":1633585226912,"image":"https://image.musinsa.com/mfile_s01/_shopstaff/250.staff_615e6af88e7a2.jpg?20211007142615"},{"title":"구은성","contents":"올리버코튼즈","link":"https://magazine.musinsa.com/index.php?m=shopstaff&_y=2021&ordw=d_regis&p=1&uid=163604","retrieved":1633585226913,"image":"https://image.musinsa.com/mfile_s01/_shopstaff/250.staff_615e6a03acc1e.jpg?20211007142428"},{"title":"백진철","contents":"집시","link":"https://magazine.musinsa.com/index.php?m=shopstaff&_y=2021&ordw=d_regis&p=1&uid=163603","retrieved":1633585226914,"image":"https://image.musinsa.com/mfile_s01/_shopstaff/250.staff_615e69b07079d.jpg?20211007142428"},{"title":"강다영","contents":"워브먼트","link":"https://magazine.musinsa.com/index.php?m=shopstaff&_y=2021&ordw=d_regis&p=1&uid=163602","retrieved":1633585226916,"image":"https://image.musinsa.com/mfile_s01/_shopstaff/250.staff_615e697742326.jpg?20211007142322"},{"title":"이현진","contents":"브릭","link":"https://magazine.musinsa.com/index.php?m=shopstaff&_y=2021&ordw=d_regis&p=1&uid=163601","retrieved":1633585226917,"image":"https://image.musinsa.com/mfile_s01/_shopstaff/250.staff_615e689f086c2.jpg?20211007142322"},{"title":"박헌준","contents":"브릭","link":"https://magazine.musinsa.com/index.php?m=shopstaff&_y=2021&ordw=d_regis&p=1&uid=163600","retrieved":1633585226918,"image":"https://image.musinsa.com/mfile_s01/_shopstaff/250.staff_615e67c1a9da6.jpg?20211007142322"},{"title":"정지오","contents":"브릭","link":"https://magazine.musinsa.com/index.php?m=shopstaff&_y=2021&ordw=d_regis&p=1&uid=163599","retrieved":1633585226919,"image":"https://image.musinsa.com/mfile_s01/_shopstaff/250.staff_615e671dd4a2c.jpg?20211007142322"},{"title":"이강운","contents":"브릭","link":"https://magazine.musinsa.com/index.php?m=shopstaff&_y=2021&ordw=d_regis&p=1&uid=163598","retrieved":1633585226920,"image":"https://image.musinsa.com/mfile_s01/_shopstaff/250.staff_615e66780314c.jpg?20211007142322"},{"title":"최형우","contents":"버켓","link":"https://magazine.musinsa.com/index.php?m=shopstaff&_y=2021&ordw=d_regis&p=1&uid=163597","retrieved":1633585226921,"image":"https://image.musinsa.com/mfile_s01/_shopstaff/250.staff_615e63bda2b44.jpg?20211007142351"},{"title":"소의","contents":"랑가주망","link":"https://magazine.musinsa.com/index.php?m=shopstaff&_y=2021&ordw=d_regis&p=1&uid=163596","retrieved":1633585226923,"image":"https://image.musinsa.com/mfile_s01/_shopstaff/250.staff_615e601602985.jpg?20211007142322"},{"title":"의석","contents":"랑가주망","link":"https://magazine.musinsa.com/index.php?m=shopstaff&_y=2021&ordw=d_regis&p=1&uid=163595","retrieved":1633585226924,"image":"https://image.musinsa.com/mfile_s01/_shopstaff/250.staff_615e5fb0b0308.jpg?20211007142322"},{"title":"혜린","contents":"랑가주망","link":"https://magazine.musinsa.com/index.php?m=shopstaff&_y=2021&ordw=d_regis&p=1&uid=163593","retrieved":1633585226925,"image":"https://image.musinsa.com/mfile_s01/_shopstaff/250.staff_615e5def7cf0a.jpg?20211007142322"},{"title":"호일","contents":"랑가주망","link":"https://magazine.musinsa.com/index.php?m=shopstaff&_y=2021&ordw=d_regis&p=1&uid=163592","retrieved":1633585226926,"image":"https://image.musinsa.com/mfile_s01/_shopstaff/250.staff_615e5d862d630.jpg?20211007142322"},{"title":"의환","contents":"랑가주망","link":"https://magazine.musinsa.com/index.php?m=shopstaff&_y=2021&ordw=d_regis&p=1&uid=163591","retrieved":1633585226927,"image":"https://image.musinsa.com/mfile_s01/_shopstaff/250.staff_615e5d19f1bfd.jpg?20211007142322"},{"title":"지수","contents":"이스트쿤스트","link":"https://magazine.musinsa.com/index.php?m=shopstaff&_y=2021&ordw=d_regis&p=1&uid=163590","retrieved":1633585226928,"image":"https://image.musinsa.com/mfile_s01/_shopstaff/250.staff_615e5c1dbb314.jpg?20211007142322"},{"title":"권꿈","contents":"이스트쿤스트","link":"https://magazine.musinsa.com/index.php?m=shopstaff&_y=2021&ordw=d_regis&p=1&uid=163589","retrieved":1633585226930,"image":"https://image.musinsa.com/mfile_s01/_shopstaff/250.staff_615e5baf8cb4b.jpg?20211007142322"},{"title":"설우","contents":"논앤논","link":"https://magazine.musinsa.com/index.php?m=shopstaff&_y=2021&ordw=d_regis&p=1&uid=163588","retrieved":1633585226931,"image":"https://image.musinsa.com/mfile_s01/_shopstaff/250.staff_615e5b605bc93.jpg?20211007142322"},{"title":"이소정","contents":"이스트쿤스트","link":"https://magazine.musinsa.com/index.php?m=shopstaff&_y=2021&ordw=d_regis&p=1&uid=163587","retrieved":1633585226932,"image":"https://image.musinsa.com/mfile_s01/_shopstaff/250.staff_615e5b44ebfb0.jpg?20211007142322"},{"title":"강찬우","contents":"부스틱서플라이","link":"https://magazine.musinsa.com/index.php?m=shopstaff&_y=2021&ordw=d_regis&p=1&uid=163586","retrieved":1633585226933,"image":"https://image.musinsa.com/mfile_s01/_shopstaff/250.staff_615e5b1739690.jpg?20211007142322"},{"title":"설우","contents":"논앤논","link":"https://magazine.musinsa.com/index.php?m=shopstaff&_y=2021&ordw=d_regis&p=1&uid=163585","retrieved":1633585226940,"image":"https://image.musinsa.com/mfile_s01/_shopstaff/250.staff_615e5b135b1aa.jpg?20211007142322"},{"title":"남현우","contents":"부스틱서플라이","link":"https://magazine.musinsa.com/index.php?m=shopstaff&_y=2021&ordw=d_regis&p=1&uid=163584","retrieved":1633585226941,"image":"https://image.musinsa.com/mfile_s01/_shopstaff/250.staff_615e5abd5c483.jpg?20211007142322"},{"title":"설우","contents":"후딩스","link":"https://magazine.musinsa.com/index.php?m=shopstaff&_y=2021&ordw=d_regis&p=1&uid=163583","retrieved":1633585226942,"image":"https://image.musinsa.com/mfile_s01/_shopstaff/250.staff_615e5a54387ba.jpg?20211007142322"},{"title":"권건우","contents":"테이크이지","link":"https://magazine.musinsa.com/index.php?m=shopstaff&_y=2021&ordw=d_regis&p=1&uid=163582","retrieved":1633585226943,"image":"https://image.musinsa.com/mfile_s01/_shopstaff/250.staff_615e5a45e72ee.jpg?20211007142322"},{"title":"찬영","contents":"이스트쿤스트","link":"https://magazine.musinsa.com/index.php?m=shopstaff&_y=2021&ordw=d_regis&p=1&uid=163581","retrieved":1633585226944,"image":"https://image.musinsa.com/mfile_s01/_shopstaff/250.staff_615e5a114355e.jpg?20211007142045"},{"title":"김은우","contents":"부스틱서플라이","link":"https://magazine.musinsa.com/index.php?m=shopstaff&_y=2021&ordw=d_regis&p=1&uid=163580","retrieved":1633585226944,"image":"https://image.musinsa.com/mfile_s01/_shopstaff/250.staff_615e5a02c0b03.jpg?20211007142028"},{"title":"박소정","contents":"테이크이지","link":"https://magazine.musinsa.com/index.php?m=shopstaff&_y=2021&ordw=d_regis&p=1&uid=163579","retrieved":1633585226952,"image":"https://image.musinsa.com/mfile_s01/_shopstaff/250.staff_615e59cddebdb.jpg?20211007142028"},{"title":"찬이","contents":"이스트쿤스트","link":"https://magazine.musinsa.com/index.php?m=shopstaff&_y=2021&ordw=d_regis&p=1&uid=163578","retrieved":1633585226953,"image":"https://image.musinsa.com/mfile_s01/_shopstaff/250.staff_615e59bb8f73c.jpg?20211007142028"},{"title":"한서웅","contents":"부스틱서플라이","link":"https://magazine.musinsa.com/index.php?m=shopstaff&_y=2021&ordw=d_regis&p=1&uid=163576","retrieved":1633585226954,"image":"https://image.musinsa.com/mfile_s01/_shopstaff/250.staff_615e5961e3e7b.jpg?20211007142028"},{"title":"한승우","contents":"테이크이지","link":"https://magazine.musinsa.com/index.php?m=shopstaff&_y=2021&ordw=d_regis&p=1&uid=163575","retrieved":1633585226954,"image":"https://image.musinsa.com/mfile_s01/_shopstaff/250.staff_615e59412ad99.jpg?20211007142028"},{"title":"황희영","contents":"테이크이지","link":"https://magazine.musinsa.com/index.php?m=shopstaff&_y=2021&ordw=d_regis&p=1&uid=163574","retrieved":1633585226955,"image":"https://image.musinsa.com/mfile_s01/_shopstaff/250.staff_615e58df7ada7.jpg?20211007142028"},{"title":"황정균","contents":"인템포무드","link":"https://magazine.musinsa.com/index.php?m=shopstaff&_y=2021&ordw=d_regis&p=1&uid=163573","retrieved":1633585226956,"image":"https://image.musinsa.com/mfile_s01/_shopstaff/250.staff_615e5874c353b.jpg?20211007142028"},{"title":"김태원","contents":"테이크이지","link":"https://magazine.musinsa.com/index.php?m=shopstaff&_y=2021&ordw=d_regis&p=1&uid=163572","retrieved":1633585226957,"image":"https://image.musinsa.com/mfile_s01/_shopstaff/250.staff_615e5860b5e63.jpg?20211007142028"},{"title":"정의석","contents":"인템포무드","link":"https://magazine.musinsa.com/index.php?m=shopstaff&_y=2021&ordw=d_regis&p=1&uid=163571","retrieved":1633585226958,"image":"https://image.musinsa.com/mfile_s01/_shopstaff/250.staff_615e5823a8b8e.jpg?20211007142028"},{"title":"고현영","contents":"휠라","link":"https://magazine.musinsa.com/index.php?m=shopstaff&_y=2021&ordw=d_regis&p=1&uid=163570","retrieved":1633585226959,"image":"https://image.musinsa.com/mfile_s01/_shopstaff/250.staff_615e57fcc853a.jpg?20211007142028"}]}