{"title":"무신사 ─ 브랜드 스냅","url":"https://magazine.musinsa.com/index.php?m=shopstaff&_y=2021&ordw=d_regis&p=1","favicon":"https://magazine.musinsa.com/favicon.ico","elements":[{"title":"고도현","contents":"에씨드슬라이드","link":"https://magazine.musinsa.com/index.php?m=shopstaff&_y=2021&ordw=d_regis&p=1&uid=165871","retrieved":1634550289880,"image":"https://image.musinsa.com/mfile_s01/_shopstaff/250.staff_616d37cbda188.jpg?20211018180956"},{"title":"정대성","contents":"어반디타입","link":"https://magazine.musinsa.com/index.php?m=shopstaff&_y=2021&ordw=d_regis&p=1&uid=165870","retrieved":1634550289881,"image":"https://image.musinsa.com/mfile_s01/_shopstaff/250.staff_616d37cb66407.jpg?20211018180956"},{"title":"조준익","contents":"에씨드슬라이드","link":"https://magazine.musinsa.com/index.php?m=shopstaff&_y=2021&ordw=d_regis&p=1&uid=165869","retrieved":1634550289882,"image":"https://image.musinsa.com/mfile_s01/_shopstaff/250.staff_616d37cad761e.jpg?20211018180956"},{"title":"조민철","contents":"어반디타입","link":"https://magazine.musinsa.com/index.php?m=shopstaff&_y=2021&ordw=d_regis&p=1&uid=165868","retrieved":1634550289888,"image":"https://image.musinsa.com/mfile_s01/_shopstaff/250.staff_616d37ca256ae.jpg?20211018180956"},{"title":"이다설","contents":"에씨드슬라이드","link":"https://magazine.musinsa.com/index.php?m=shopstaff&_y=2021&ordw=d_regis&p=1&uid=165867","retrieved":1634550289889,"image":"https://image.musinsa.com/mfile_s01/_shopstaff/250.staff_616d37c9dbd01.jpg?20211018180956"},{"title":"김가희","contents":"에씨드슬라이드","link":"https://magazine.musinsa.com/index.php?m=shopstaff&_y=2021&ordw=d_regis&p=1&uid=165866","retrieved":1634550289890,"image":"https://image.musinsa.com/mfile_s01/_shopstaff/250.staff_616d37c904025.jpg?20211018180956"},{"title":"김도연","contents":"로어링라드","link":"https://magazine.musinsa.com/index.php?m=shopstaff&_y=2021&ordw=d_regis&p=1&uid=165865","retrieved":1634550289891,"image":"https://image.musinsa.com/mfile_s01/_shopstaff/250.staff_616d37c8d1c54.jpg?20211018180956"},{"title":"맹은진","contents":"에씨드슬라이드","link":"https://magazine.musinsa.com/index.php?m=shopstaff&_y=2021&ordw=d_regis&p=1&uid=165864","retrieved":1634550289892,"image":"https://image.musinsa.com/mfile_s01/_shopstaff/250.staff_616d37c816f54.jpg?20211018180956"},{"title":"윤윤주","contents":"어반디타입","link":"https://magazine.musinsa.com/index.php?m=shopstaff&_y=2021&ordw=d_regis&p=1&uid=165863","retrieved":1634550289893,"image":"https://image.musinsa.com/mfile_s01/_shopstaff/250.staff_616d37c7442e7.jpg?20211018180956"},{"title":"성상영","contents":"섹스토","link":"https://magazine.musinsa.com/index.php?m=shopstaff&_y=2021&ordw=d_regis&p=1&uid=165862","retrieved":1634550289894,"image":"https://image.musinsa.com/mfile_s01/_shopstaff/250.staff_616d37c6014e9.jpg?20211018180956"},{"title":"이우주","contents":"어반디타입","link":"https://magazine.musinsa.com/index.php?m=shopstaff&_y=2021&ordw=d_regis&p=1&uid=165861","retrieved":1634550289894,"image":"https://image.musinsa.com/mfile_s01/_shopstaff/250.staff_616d37c5cc48c.jpg?20211018180956"},{"title":"문경","contents":"바잘","link":"https://magazine.musinsa.com/index.php?m=shopstaff&_y=2021&ordw=d_regis&p=1&uid=165860","retrieved":1634550289895,"image":"https://image.musinsa.com/mfile_s01/_shopstaff/250.staff_616d379eb349a.jpg?20211018180956"},{"title":"JM","contents":"스테이지 네임","link":"https://magazine.musinsa.com/index.php?m=shopstaff&_y=2021&ordw=d_regis&p=1&uid=165859","retrieved":1634550289896,"image":"https://image.musinsa.com/mfile_s01/_shopstaff/250.staff_616d379750f8f.jpg?20211018180956"},{"title":"유다미","contents":"로어링라드","link":"https://magazine.musinsa.com/index.php?m=shopstaff&_y=2021&ordw=d_regis&p=1&uid=165858","retrieved":1634550289904,"image":"https://image.musinsa.com/mfile_s01/_shopstaff/250.staff_616d3795ad7c0.jpg?20211018180956"},{"title":"박효빈","contents":"어텐션로우","link":"https://magazine.musinsa.com/index.php?m=shopstaff&_y=2021&ordw=d_regis&p=1&uid=165857","retrieved":1634550289904,"image":"https://image.musinsa.com/mfile_s01/_shopstaff/250.staff_616d378d29664.jpg?20211018180956"},{"title":"우림","contents":"바잘","link":"https://magazine.musinsa.com/index.php?m=shopstaff&_y=2021&ordw=d_regis&p=1&uid=165856","retrieved":1634550289905,"image":"https://image.musinsa.com/mfile_s01/_shopstaff/250.staff_616d375babe66.jpg?20211018180551"},{"title":"한희섭","contents":"브라운브레스","link":"https://magazine.musinsa.com/index.php?m=shopstaff&_y=2021&ordw=d_regis&p=1&uid=165855","retrieved":1634550289905,"image":"https://image.musinsa.com/mfile_s01/_shopstaff/250.staff_616d369813e8c.jpg?20211018180551"},{"title":"박성호","contents":"리플라이퍼키","link":"https://magazine.musinsa.com/index.php?m=shopstaff&_y=2021&ordw=d_regis&p=1&uid=165854","retrieved":1634550289905,"image":"https://image.musinsa.com/mfile_s01/_shopstaff/250.staff_616d360350d34.jpg?20211018180507"},{"title":"김정호","contents":"리플라이퍼키","link":"https://magazine.musinsa.com/index.php?m=shopstaff&_y=2021&ordw=d_regis&p=1&uid=165853","retrieved":1634550289907,"image":"https://image.musinsa.com/mfile_s01/_shopstaff/250.staff_616d35de7ac72.jpg?20211018180507"},{"title":"조의환","contents":"라이프 아카이브","link":"https://magazine.musinsa.com/index.php?m=shopstaff&_y=2021&ordw=d_regis&p=1&uid=165852","retrieved":1634550289908,"image":"https://image.musinsa.com/mfile_s01/_shopstaff/250.staff_616d35bf72459.jpg?20211018180507"},{"title":"최현지","contents":"라이프 아카이브","link":"https://magazine.musinsa.com/index.php?m=shopstaff&_y=2021&ordw=d_regis&p=1&uid=165851","retrieved":1634550289910,"image":"https://image.musinsa.com/mfile_s01/_shopstaff/250.staff_616d35ba8443a.jpg?20211018180507"},{"title":"이다정","contents":"라이프 아카이브","link":"https://magazine.musinsa.com/index.php?m=shopstaff&_y=2021&ordw=d_regis&p=1&uid=165850","retrieved":1634550289914,"image":"https://image.musinsa.com/mfile_s01/_shopstaff/250.staff_616d35b57473f.jpg?20211018180507"},{"title":"정영호","contents":"라이프 아카이브","link":"https://magazine.musinsa.com/index.php?m=shopstaff&_y=2021&ordw=d_regis&p=1&uid=165849","retrieved":1634550289915,"image":"https://image.musinsa.com/mfile_s01/_shopstaff/250.staff_616d35b09db71.jpg?20211018180551"},{"title":"김대한","contents":"리플라이퍼키","link":"https://magazine.musinsa.com/index.php?m=shopstaff&_y=2021&ordw=d_regis&p=1&uid=165848","retrieved":1634550289916,"image":"https://image.musinsa.com/mfile_s01/_shopstaff/250.staff_616d359ea711a.jpg?20211018180507"},{"title":"유정우","contents":"브라운브레스","link":"https://magazine.musinsa.com/index.php?m=shopstaff&_y=2021&ordw=d_regis&p=1&uid=165847","retrieved":1634550289917,"image":"https://image.musinsa.com/mfile_s01/_shopstaff/250.staff_616d3511e9c8e.jpg?20211018180507"},{"title":"임다슬","contents":"모더먼트","link":"https://magazine.musinsa.com/index.php?m=shopstaff&_y=2021&ordw=d_regis&p=1&uid=165846","retrieved":1634550289918,"image":"https://image.musinsa.com/mfile_s01/_shopstaff/250.staff_616d33f6e181b.jpg?20211018180507"},{"title":"이승민","contents":"로어즈","link":"https://magazine.musinsa.com/index.php?m=shopstaff&_y=2021&ordw=d_regis&p=1&uid=165845","retrieved":1634550289919,"image":"https://image.musinsa.com/mfile_s01/_shopstaff/250.staff_616d32fe65455.jpg?20211018180507"},{"title":"이승준","contents":"밀로","link":"https://magazine.musinsa.com/index.php?m=shopstaff&_y=2021&ordw=d_regis&p=1&uid=165844","retrieved":1634550289923,"image":"https://image.musinsa.com/mfile_s01/_shopstaff/250.staff_616d328332318.jpg?20211018180507"},{"title":"박성우","contents":"유니온발란트","link":"https://magazine.musinsa.com/index.php?m=shopstaff&_y=2021&ordw=d_regis&p=1&uid=165843","retrieved":1634550289923,"image":"https://image.musinsa.com/mfile_s01/_shopstaff/250.staff_616d3169b4f71.jpg?20211018180507"},{"title":"이찬율","contents":"엠엠아이씨","link":"https://magazine.musinsa.com/index.php?m=shopstaff&_y=2021&ordw=d_regis&p=1&uid=165842","retrieved":1634550289924,"image":"https://image.musinsa.com/mfile_s01/_shopstaff/250.staff_616d314c90832.jpg?20211018180507"},{"title":"한빈","contents":"르아르","link":"https://magazine.musinsa.com/index.php?m=shopstaff&_y=2021&ordw=d_regis&p=1&uid=165841","retrieved":1634550289925,"image":"https://image.musinsa.com/mfile_s01/_shopstaff/250.staff_616d312d66087.jpg?20211018180507"},{"title":"용광민","contents":"시그니처","link":"https://magazine.musinsa.com/index.php?m=shopstaff&_y=2021&ordw=d_regis&p=1&uid=165840","retrieved":1634550289926,"image":"https://image.musinsa.com/mfile_s01/_shopstaff/250.staff_616d30ab5c926.jpg?20211018180507"},{"title":"이현진","contents":"시그니처","link":"https://magazine.musinsa.com/index.php?m=shopstaff&_y=2021&ordw=d_regis&p=1&uid=165839","retrieved":1634550289926,"image":"https://image.musinsa.com/mfile_s01/_shopstaff/250.staff_616d30a51ca2e.jpg?20211018180507"},{"title":"백건우","contents":"시그니처","link":"https://magazine.musinsa.com/index.php?m=shopstaff&_y=2021&ordw=d_regis&p=1&uid=165838","retrieved":1634550289927,"image":"https://image.musinsa.com/mfile_s01/_shopstaff/250.staff_616d309c2d506.jpg?20211018180507"},{"title":"어진","contents":"르아르","link":"https://magazine.musinsa.com/index.php?m=shopstaff&_y=2021&ordw=d_regis&p=1&uid=165837","retrieved":1634550289929,"image":"https://image.musinsa.com/mfile_s01/_shopstaff/250.staff_616d307ba4041.jpg?20211018180507"},{"title":"이예진","contents":"본하이커","link":"https://magazine.musinsa.com/index.php?m=shopstaff&_y=2021&ordw=d_regis&p=1&uid=165836","retrieved":1634550289930,"image":"https://image.musinsa.com/mfile_s01/_shopstaff/250.staff_616d305a8a3ce.jpg?20211018180507"},{"title":"한빈","contents":"르아르","link":"https://magazine.musinsa.com/index.php?m=shopstaff&_y=2021&ordw=d_regis&p=1&uid=165835","retrieved":1634550289930,"image":"https://image.musinsa.com/mfile_s01/_shopstaff/250.staff_616d2ff521278.jpg?20211018180507"},{"title":"정소의","contents":"바이바이올","link":"https://magazine.musinsa.com/index.php?m=shopstaff&_y=2021&ordw=d_regis&p=1&uid=165834","retrieved":1634550289942,"image":"https://image.musinsa.com/mfile_s01/_shopstaff/250.staff_616d2fef314d7.jpg?20211018175341"},{"title":"정종호","contents":"와일드띵스","link":"https://magazine.musinsa.com/index.php?m=shopstaff&_y=2021&ordw=d_regis&p=1&uid=165833","retrieved":1634550289943,"image":"https://image.musinsa.com/mfile_s01/_shopstaff/250.staff_616d2feaec6c0.jpg?20211018175341"},{"title":"오석현","contents":"와일드띵스","link":"https://magazine.musinsa.com/index.php?m=shopstaff&_y=2021&ordw=d_regis&p=1&uid=165832","retrieved":1634550289944,"image":"https://image.musinsa.com/mfile_s01/_shopstaff/250.staff_616d2f8286891.jpg?20211018175325"},{"title":"박훈민","contents":"리프클로딩","link":"https://magazine.musinsa.com/index.php?m=shopstaff&_y=2021&ordw=d_regis&p=1&uid=165831","retrieved":1634550289945,"image":"https://image.musinsa.com/mfile_s01/_shopstaff/250.staff_616d2f4ae679d.jpg?20211018175325"},{"title":"강동원","contents":"리프클로딩","link":"https://magazine.musinsa.com/index.php?m=shopstaff&_y=2021&ordw=d_regis&p=1&uid=165830","retrieved":1634550289946,"image":"https://image.musinsa.com/mfile_s01/_shopstaff/250.staff_616d2db719080.jpg?20211018175325"},{"title":"김진아","contents":"디오스피스","link":"https://magazine.musinsa.com/index.php?m=shopstaff&_y=2021&ordw=d_regis&p=1&uid=165829","retrieved":1634550289947,"image":"https://image.musinsa.com/mfile_s01/_shopstaff/250.staff_616d2d93291f5.jpg?20211018175325"},{"title":"류지엽","contents":"와일드띵스","link":"https://magazine.musinsa.com/index.php?m=shopstaff&_y=2021&ordw=d_regis&p=1&uid=165828","retrieved":1634550289948,"image":"https://image.musinsa.com/mfile_s01/_shopstaff/250.staff_616d2d32dc560.jpg?20211018175325"},{"title":"서동현","contents":"드로우핏","link":"https://magazine.musinsa.com/index.php?m=shopstaff&_y=2021&ordw=d_regis&p=1&uid=165827","retrieved":1634550289949,"image":"https://image.musinsa.com/mfile_s01/_shopstaff/250.staff_616d2d327af5e.jpg?20211018175237"},{"title":"조준익","contents":"유니온발란트","link":"https://magazine.musinsa.com/index.php?m=shopstaff&_y=2021&ordw=d_regis&p=1&uid=165826","retrieved":1634550289950,"image":"https://image.musinsa.com/mfile_s01/_shopstaff/250.staff_616d2c7db6d67.jpg?20211018175237"},{"title":"이동걸","contents":"와이케이","link":"https://magazine.musinsa.com/index.php?m=shopstaff&_y=2021&ordw=d_regis&p=1&uid=165824","retrieved":1634550289951,"image":"https://image.musinsa.com/mfile_s01/_shopstaff/250.staff_616d2b5d39496.jpg?20211018175237"},{"title":"이강민","contents":"드로우핏","link":"https://magazine.musinsa.com/index.php?m=shopstaff&_y=2021&ordw=d_regis&p=1&uid=165823","retrieved":1634550289954,"image":"https://image.musinsa.com/mfile_s01/_shopstaff/250.staff_616d2b48a11df.jpg?20211018175237"},{"title":"배소희","contents":"커버낫","link":"https://magazine.musinsa.com/index.php?m=shopstaff&_y=2021&ordw=d_regis&p=1&uid=165822","retrieved":1634550289954,"image":"https://image.musinsa.com/mfile_s01/_shopstaff/250.staff_616d2b0b85cea.jpg?20211018175237"},{"title":"이혜연","contents":"안다르","link":"https://magazine.musinsa.com/index.php?m=shopstaff&_y=2021&ordw=d_regis&p=1&uid=165821","retrieved":1634550289955,"image":"https://image.musinsa.com/mfile_s01/_shopstaff/250.staff_616d2af7e8a6e.jpg?20211018175237"},{"title":"강동원","contents":"리프클로딩","link":"https://magazine.musinsa.com/index.php?m=shopstaff&_y=2021&ordw=d_regis&p=1&uid=165820","retrieved":1634550289956,"image":"https://image.musinsa.com/mfile_s01/_shopstaff/250.staff_616d2a517c37b.jpg?20211018175237"},{"title":"이재성","contents":"유니온발란트","link":"https://magazine.musinsa.com/index.php?m=shopstaff&_y=2021&ordw=d_regis&p=1&uid=165818","retrieved":1634550289957,"image":"https://image.musinsa.com/mfile_s01/_shopstaff/250.staff_616d29d733b53.jpg?20211018175237"},{"title":"오태식","contents":"안다르","link":"https://magazine.musinsa.com/index.php?m=shopstaff&_y=2021&ordw=d_regis&p=1&uid=165817","retrieved":1634550289958,"image":"https://image.musinsa.com/mfile_s01/_shopstaff/250.staff_616d2bc774d9c.jpg?20211018175237"},{"title":"백수련","contents":"와이케이","link":"https://magazine.musinsa.com/index.php?m=shopstaff&_y=2021&ordw=d_regis&p=1&uid=165816","retrieved":1634550289959,"image":"https://image.musinsa.com/mfile_s01/_shopstaff/250.staff_616d294a76f62.jpg?20211018175237"},{"title":"박승찬","contents":"와이케이","link":"https://magazine.musinsa.com/index.php?m=shopstaff&_y=2021&ordw=d_regis&p=1&uid=165815","retrieved":1634550289960,"image":"https://image.musinsa.com/mfile_s01/_shopstaff/250.staff_616d290d00cac.jpg?20211018175237"},{"title":"이현기","contents":"유니온발란트","link":"https://magazine.musinsa.com/index.php?m=shopstaff&_y=2021&ordw=d_regis&p=1&uid=165811","retrieved":1634550289961,"image":"https://image.musinsa.com/mfile_s01/_shopstaff/250.staff_616d2821599df.jpg?20211018175237"},{"title":"Wet Boy","contents":"알디브이제트","link":"https://magazine.musinsa.com/index.php?m=shopstaff&_y=2021&ordw=d_regis&p=1&uid=165810","retrieved":1634550289962,"image":"https://image.musinsa.com/mfile_s01/_shopstaff/250.staff_616d2807d1f1c.jpg?20211018175237"},{"title":"이선혜","contents":"니티드","link":"https://magazine.musinsa.com/index.php?m=shopstaff&_y=2021&ordw=d_regis&p=1&uid=165809","retrieved":1634550289962,"image":"https://image.musinsa.com/mfile_s01/_shopstaff/250.staff_616d27cfe42a7.jpg?20211018175237"},{"title":"김채운","contents":"니티드","link":"https://magazine.musinsa.com/index.php?m=shopstaff&_y=2021&ordw=d_regis&p=1&uid=165808","retrieved":1634550289964,"image":"https://image.musinsa.com/mfile_s01/_shopstaff/250.staff_616d277192a52.jpg?20211018175237"},{"title":"정의석","contents":"유니온발란트","link":"https://magazine.musinsa.com/index.php?m=shopstaff&_y=2021&ordw=d_regis&p=1&uid=165807","retrieved":1634550289968,"image":"https://image.musinsa.com/mfile_s01/_shopstaff/250.staff_616d276d72d62.jpg?20211018175237"}]}