{"title":"무신사 ─ 브랜드 스냅","url":"https://magazine.musinsa.com/index.php?m=shopstaff&_y=2021&ordw=d_regis&p=1","favicon":"https://magazine.musinsa.com/favicon.ico","elements":[{"title":"성상영","contents":"섹스토","link":"https://magazine.musinsa.com/index.php?m=shopstaff&_y=2021&ordw=d_regis&p=1&uid=167722","retrieved":1635241734209,"image":"https://image.musinsa.com/mfile_s01/_shopstaff/250.staff_6177c3c74ec9f.jpg?20211026180512"},{"title":"강예지","contents":"아더월들리","link":"https://magazine.musinsa.com/index.php?m=shopstaff&_y=2021&ordw=d_regis&p=1&uid=167721","retrieved":1635241734211,"image":"https://image.musinsa.com/mfile_s01/_shopstaff/250.staff_6177c3c46cb6b.jpg?20211026180512"},{"title":"구자현","contents":"어텐션로우","link":"https://magazine.musinsa.com/index.php?m=shopstaff&_y=2021&ordw=d_regis&p=1&uid=167720","retrieved":1635241734212,"image":"https://image.musinsa.com/mfile_s01/_shopstaff/250.staff_6177c3bc2a75a.jpg?20211026180512"},{"title":"김승현","contents":"브랜디드","link":"https://magazine.musinsa.com/index.php?m=shopstaff&_y=2021&ordw=d_regis&p=1&uid=167719","retrieved":1635241734213,"image":"https://image.musinsa.com/mfile_s01/_shopstaff/250.staff_6177c3a0e85b5.jpg?20211026180512"},{"title":"JM","contents":"스테이지 네임","link":"https://magazine.musinsa.com/index.php?m=shopstaff&_y=2021&ordw=d_regis&p=1&uid=167718","retrieved":1635241734216,"image":"https://image.musinsa.com/mfile_s01/_shopstaff/250.staff_6177c3a0392ac.jpg?20211026180512"},{"title":"강다희","contents":"브랜디드","link":"https://magazine.musinsa.com/index.php?m=shopstaff&_y=2021&ordw=d_regis&p=1&uid=167717","retrieved":1635241734216,"image":"https://image.musinsa.com/mfile_s01/_shopstaff/250.staff_6177c39cd1d63.jpg?20211026180512"},{"title":"김동한","contents":"엘무드","link":"https://magazine.musinsa.com/index.php?m=shopstaff&_y=2021&ordw=d_regis&p=1&uid=167716","retrieved":1635241734218,"image":"https://image.musinsa.com/mfile_s01/_shopstaff/250.staff_6177c35a8cd45.jpg?20211026180512"},{"title":"김예지","contents":"로르인","link":"https://magazine.musinsa.com/index.php?m=shopstaff&_y=2021&ordw=d_regis&p=1&uid=167715","retrieved":1635241734220,"image":"https://image.musinsa.com/mfile_s01/_shopstaff/250.staff_6177c35761906.jpg?20211026180512"},{"title":"김지혜","contents":"로르인","link":"https://magazine.musinsa.com/index.php?m=shopstaff&_y=2021&ordw=d_regis&p=1&uid=167714","retrieved":1635241734220,"image":"https://image.musinsa.com/mfile_s01/_shopstaff/250.staff_6177c34f2e250.jpg?20211026180250"},{"title":"이진식","contents":"어퍼스트로피 콤마","link":"https://magazine.musinsa.com/index.php?m=shopstaff&_y=2021&ordw=d_regis&p=1&uid=167713","retrieved":1635241734220,"image":"https://image.musinsa.com/mfile_s01/_shopstaff/250.staff_6177c32636aa6.jpg?20211026180250"},{"title":"한단비","contents":"라이프 아카이브","link":"https://magazine.musinsa.com/index.php?m=shopstaff&_y=2021&ordw=d_regis&p=1&uid=167711","retrieved":1635241734220,"image":"https://image.musinsa.com/mfile_s01/_shopstaff/250.staff_6177c306197c8.jpg?20211026180250"},{"title":"김민서","contents":"리플라이퍼키","link":"https://magazine.musinsa.com/index.php?m=shopstaff&_y=2021&ordw=d_regis&p=1&uid=167710","retrieved":1635241734220,"image":"https://image.musinsa.com/mfile_s01/_shopstaff/250.staff_6177c30514317.jpg?20211026180250"},{"title":"지민우","contents":"라이프 아카이브","link":"https://magazine.musinsa.com/index.php?m=shopstaff&_y=2021&ordw=d_regis&p=1&uid=167709","retrieved":1635241734220,"image":"https://image.musinsa.com/mfile_s01/_shopstaff/250.staff_6177c2fe8ae64.jpg?20211026180250"},{"title":"김동한","contents":"엘무드","link":"https://magazine.musinsa.com/index.php?m=shopstaff&_y=2021&ordw=d_regis&p=1&uid=167708","retrieved":1635241734221,"image":"https://image.musinsa.com/mfile_s01/_shopstaff/250.staff_6177c2eb5633e.jpg?20211026180250"},{"title":"서원재","contents":"리플라이퍼키","link":"https://magazine.musinsa.com/index.php?m=shopstaff&_y=2021&ordw=d_regis&p=1&uid=167707","retrieved":1635241734222,"image":"https://image.musinsa.com/mfile_s01/_shopstaff/250.staff_6177c2d2d42c4.jpg?20211026180250"},{"title":"이준영","contents":"리플라이퍼키","link":"https://magazine.musinsa.com/index.php?m=shopstaff&_y=2021&ordw=d_regis&p=1&uid=167706","retrieved":1635241734223,"image":"https://image.musinsa.com/mfile_s01/_shopstaff/250.staff_6177c29a10ff3.jpg?20211026180250"},{"title":"이진우","contents":"네스티킥","link":"https://magazine.musinsa.com/index.php?m=shopstaff&_y=2021&ordw=d_regis&p=1&uid=167705","retrieved":1635241734224,"image":"https://image.musinsa.com/mfile_s01/_shopstaff/250.staff_6177c262d2460.jpg?20211026180250"},{"title":"강다은","contents":"스파오","link":"https://magazine.musinsa.com/index.php?m=shopstaff&_y=2021&ordw=d_regis&p=1&uid=167704","retrieved":1635241734225,"image":"https://image.musinsa.com/mfile_s01/_shopstaff/250.staff_6177c24a1f20b.jpg?20211026180250"},{"title":"류현","contents":"칸코","link":"https://magazine.musinsa.com/index.php?m=shopstaff&_y=2021&ordw=d_regis&p=1&uid=167703","retrieved":1635241734226,"image":"https://image.musinsa.com/mfile_s01/_shopstaff/250.staff_6177c224e12ff.jpg?20211026180250"},{"title":"이나경","contents":"스파오","link":"https://magazine.musinsa.com/index.php?m=shopstaff&_y=2021&ordw=d_regis&p=1&uid=167702","retrieved":1635241734227,"image":"https://image.musinsa.com/mfile_s01/_shopstaff/250.staff_6177c1a9ef730.jpg?20211026180250"},{"title":"루비","contents":"나이스고스트클럽","link":"https://magazine.musinsa.com/index.php?m=shopstaff&_y=2021&ordw=d_regis&p=1&uid=167701","retrieved":1635241734228,"image":"https://image.musinsa.com/mfile_s01/_shopstaff/250.staff_6177c123b560c.jpg?20211026175856"},{"title":"루비","contents":"나이스고스트클럽","link":"https://magazine.musinsa.com/index.php?m=shopstaff&_y=2021&ordw=d_regis&p=1&uid=167700","retrieved":1635241734229,"image":"https://image.musinsa.com/mfile_s01/_shopstaff/250.staff_6177c07f03805.jpg?20211026175856"},{"title":"오현석","contents":"스파오","link":"https://magazine.musinsa.com/index.php?m=shopstaff&_y=2021&ordw=d_regis&p=1&uid=167699","retrieved":1635241734230,"image":"https://image.musinsa.com/mfile_s01/_shopstaff/250.staff_6177c07d7e16a.jpg?20211026175856"},{"title":"김희창","contents":"스파오","link":"https://magazine.musinsa.com/index.php?m=shopstaff&_y=2021&ordw=d_regis&p=1&uid=167698","retrieved":1635241734230,"image":"https://image.musinsa.com/mfile_s01/_shopstaff/250.staff_6177c01179730.jpg?20211026175856"},{"title":"루비","contents":"나이스고스트클럽","link":"https://magazine.musinsa.com/index.php?m=shopstaff&_y=2021&ordw=d_regis&p=1&uid=167697","retrieved":1635241734232,"image":"https://image.musinsa.com/mfile_s01/_shopstaff/250.staff_6177bfc1d4611.jpg?20211026175856"},{"title":"김태수","contents":"킹아카이브","link":"https://magazine.musinsa.com/index.php?m=shopstaff&_y=2021&ordw=d_regis&p=1&uid=167696","retrieved":1635241734232,"image":"https://image.musinsa.com/mfile_s01/_shopstaff/250.staff_6177bf6055375.jpg?20211026175856"},{"title":"고현영","contents":"스파오","link":"https://magazine.musinsa.com/index.php?m=shopstaff&_y=2021&ordw=d_regis&p=1&uid=167695","retrieved":1635241734232,"image":"https://image.musinsa.com/mfile_s01/_shopstaff/250.staff_6177bf3727a41.jpg?20211026175819"},{"title":"루비","contents":"나이스고스트클럽","link":"https://magazine.musinsa.com/index.php?m=shopstaff&_y=2021&ordw=d_regis&p=1&uid=167694","retrieved":1635241734233,"image":"https://image.musinsa.com/mfile_s01/_shopstaff/250.staff_6177bec7b50d8.jpg?20211026175819"},{"title":"루비","contents":"나이스고스트클럽","link":"https://magazine.musinsa.com/index.php?m=shopstaff&_y=2021&ordw=d_regis&p=1&uid=167693","retrieved":1635241734236,"image":"https://image.musinsa.com/mfile_s01/_shopstaff/250.staff_6177be076f498.jpg?20211026175819"},{"title":"jsy","contents":"브루먼","link":"https://magazine.musinsa.com/index.php?m=shopstaff&_y=2021&ordw=d_regis&p=1&uid=167692","retrieved":1635241734238,"image":"https://image.musinsa.com/mfile_s01/_shopstaff/250.staff_6177bdb6b4456.jpg?20211026175819"},{"title":"윤아","contents":"마크엠","link":"https://magazine.musinsa.com/index.php?m=shopstaff&_y=2021&ordw=d_regis&p=1&uid=167691","retrieved":1635241734238,"image":"https://image.musinsa.com/mfile_s01/_shopstaff/250.staff_6177bd5984173.jpg?20211026175819"},{"title":"유희","contents":"마크엠","link":"https://magazine.musinsa.com/index.php?m=shopstaff&_y=2021&ordw=d_regis&p=1&uid=167690","retrieved":1635241734240,"image":"https://image.musinsa.com/mfile_s01/_shopstaff/250.staff_6177bd2d07a78.jpg?20211026175819"},{"title":"배기웅","contents":"누벨바그 코리아","link":"https://magazine.musinsa.com/index.php?m=shopstaff&_y=2021&ordw=d_regis&p=1&uid=167689","retrieved":1635241734241,"image":"https://image.musinsa.com/mfile_s01/_shopstaff/250.staff_6177bd1755b81.jpg?20211026175819"},{"title":"유빈","contents":"마크엠","link":"https://magazine.musinsa.com/index.php?m=shopstaff&_y=2021&ordw=d_regis&p=1&uid=167688","retrieved":1635241734246,"image":"https://image.musinsa.com/mfile_s01/_shopstaff/250.staff_6177bd09c4258.jpg?20211026175726"},{"title":"강욱","contents":"에노우","link":"https://magazine.musinsa.com/index.php?m=shopstaff&_y=2021&ordw=d_regis&p=1&uid=167687","retrieved":1635241734246,"image":"https://image.musinsa.com/mfile_s01/_shopstaff/250.staff_6177bce5b6c64.jpg?20211026175718"},{"title":"예니","contents":"오프오스","link":"https://magazine.musinsa.com/index.php?m=shopstaff&_y=2021&ordw=d_regis&p=1&uid=167686","retrieved":1635241734247,"image":"https://image.musinsa.com/mfile_s01/_shopstaff/250.staff_6177bcb11f478.jpg?20211026175718"},{"title":"수이","contents":"오프오스","link":"https://magazine.musinsa.com/index.php?m=shopstaff&_y=2021&ordw=d_regis&p=1&uid=167685","retrieved":1635241734248,"image":"https://image.musinsa.com/mfile_s01/_shopstaff/250.staff_6177bc82c9bf8.jpg?20211026175706"},{"title":"유정","contents":"오프오스","link":"https://magazine.musinsa.com/index.php?m=shopstaff&_y=2021&ordw=d_regis&p=1&uid=167684","retrieved":1635241734249,"image":"https://image.musinsa.com/mfile_s01/_shopstaff/250.staff_6177bc4a75ddc.jpg?20211026175706"},{"title":"유리","contents":"에노우","link":"https://magazine.musinsa.com/index.php?m=shopstaff&_y=2021&ordw=d_regis&p=1&uid=167683","retrieved":1635241734250,"image":"https://image.musinsa.com/mfile_s01/_shopstaff/250.staff_6177bc163fb01.jpg?20211026175706"},{"title":"이동걸","contents":"피스워커","link":"https://magazine.musinsa.com/index.php?m=shopstaff&_y=2021&ordw=d_regis&p=1&uid=167681","retrieved":1635241734263,"image":"https://image.musinsa.com/mfile_s01/_shopstaff/250.staff_6177bb85da69c.jpg?20211026175328"},{"title":"고건우","contents":"피스워커","link":"https://magazine.musinsa.com/index.php?m=shopstaff&_y=2021&ordw=d_regis&p=1&uid=167680","retrieved":1635241734264,"image":"https://image.musinsa.com/mfile_s01/_shopstaff/250.staff_6177bb3dc35c8.jpg?20211026175114"},{"title":"고민성","contents":"크럼프","link":"https://magazine.musinsa.com/index.php?m=shopstaff&_y=2021&ordw=d_regis&p=1&uid=167679","retrieved":1635241734265,"image":"https://image.musinsa.com/mfile_s01/_shopstaff/250.staff_6177bb3c0205d.jpg?20211026175114"},{"title":"조준익","contents":"피스워커","link":"https://magazine.musinsa.com/index.php?m=shopstaff&_y=2021&ordw=d_regis&p=1&uid=167678","retrieved":1635241734267,"image":"https://image.musinsa.com/mfile_s01/_shopstaff/250.staff_6177baea37506.jpg?20211026175114"},{"title":"설우","contents":"논앤논","link":"https://magazine.musinsa.com/index.php?m=shopstaff&_y=2021&ordw=d_regis&p=1&uid=167677","retrieved":1635241734297,"image":"https://image.musinsa.com/mfile_s01/_shopstaff/250.staff_6177ba9a361a4.jpg?20211026175114"},{"title":"윤재훈","contents":"피스워커","link":"https://magazine.musinsa.com/index.php?m=shopstaff&_y=2021&ordw=d_regis&p=1&uid=167676","retrieved":1635241734308,"image":"https://image.musinsa.com/mfile_s01/_shopstaff/250.staff_6177ba91cb9de.jpg?20211026175114"},{"title":"장누리","contents":"폴스부띠끄","link":"https://magazine.musinsa.com/index.php?m=shopstaff&_y=2021&ordw=d_regis&p=1&uid=167675","retrieved":1635241734311,"image":"https://image.musinsa.com/mfile_s01/_shopstaff/250.staff_6177ba6a52393.jpg?20211026175114"},{"title":"설우","contents":"논앤논","link":"https://magazine.musinsa.com/index.php?m=shopstaff&_y=2021&ordw=d_regis&p=1&uid=167674","retrieved":1635241734311,"image":"https://image.musinsa.com/mfile_s01/_shopstaff/250.staff_6177ba41526bc.jpg?20211026175114"},{"title":"정종호","contents":"피스워커","link":"https://magazine.musinsa.com/index.php?m=shopstaff&_y=2021&ordw=d_regis&p=1&uid=167673","retrieved":1635241734311,"image":"https://image.musinsa.com/mfile_s01/_shopstaff/250.staff_6177ba33882a8.jpg?20211026175114"},{"title":"설우","contents":"논앤논","link":"https://magazine.musinsa.com/index.php?m=shopstaff&_y=2021&ordw=d_regis&p=1&uid=167672","retrieved":1635241734312,"image":"https://image.musinsa.com/mfile_s01/_shopstaff/250.staff_6177b9da8f7a3.jpg?20211026175114"},{"title":"문희주","contents":"브라운브레스","link":"https://magazine.musinsa.com/index.php?m=shopstaff&_y=2021&ordw=d_regis&p=1&uid=167671","retrieved":1635241734317,"image":"https://image.musinsa.com/mfile_s01/_shopstaff/250.staff_6177b9d1b45df.jpg?20211026175114"},{"title":"김세진","contents":"왓더","link":"https://magazine.musinsa.com/index.php?m=shopstaff&_y=2021&ordw=d_regis&p=1&uid=167669","retrieved":1635241734318,"image":"https://image.musinsa.com/mfile_s01/_shopstaff/250.staff_6177b93751e17.jpg?20211026175328"},{"title":"윤성현","contents":"브라운브레스","link":"https://magazine.musinsa.com/index.php?m=shopstaff&_y=2021&ordw=d_regis&p=1&uid=167668","retrieved":1635241734320,"image":"https://image.musinsa.com/mfile_s01/_shopstaff/250.staff_6177b9273e426.jpg?20211026175328"},{"title":"박민재","contents":"브라운브레스","link":"https://magazine.musinsa.com/index.php?m=shopstaff&_y=2021&ordw=d_regis&p=1&uid=167667","retrieved":1635241734322,"image":"https://image.musinsa.com/mfile_s01/_shopstaff/250.staff_6177b8644b71a.jpg?20211026175114"},{"title":"LIA","contents":"코이무이","link":"https://magazine.musinsa.com/index.php?m=shopstaff&_y=2021&ordw=d_regis&p=1&uid=167666","retrieved":1635241734323,"image":"https://image.musinsa.com/mfile_s01/_shopstaff/250.staff_6177b84877e21.jpg?20211026175114"},{"title":"김영진","contents":"어썸스튜디오","link":"https://magazine.musinsa.com/index.php?m=shopstaff&_y=2021&ordw=d_regis&p=1&uid=167665","retrieved":1635241734325,"image":"https://image.musinsa.com/mfile_s01/_shopstaff/250.staff_6177b819c18dd.jpg?20211026175114"},{"title":"김준세","contents":"어썸스튜디오","link":"https://magazine.musinsa.com/index.php?m=shopstaff&_y=2021&ordw=d_regis&p=1&uid=167664","retrieved":1635241734327,"image":"https://image.musinsa.com/mfile_s01/_shopstaff/250.staff_6177b7dba7283.jpg?20211026175114"},{"title":"유선호","contents":"브라운브레스","link":"https://magazine.musinsa.com/index.php?m=shopstaff&_y=2021&ordw=d_regis&p=1&uid=167663","retrieved":1635241734329,"image":"https://image.musinsa.com/mfile_s01/_shopstaff/250.staff_6177b78d99419.jpg?20211026175114"},{"title":"다설","contents":"피엠코","link":"https://magazine.musinsa.com/index.php?m=shopstaff&_y=2021&ordw=d_regis&p=1&uid=167662","retrieved":1635241734330,"image":"https://image.musinsa.com/mfile_s01/_shopstaff/250.staff_6177b78885777.jpg?20211026175114"},{"title":"설우","contents":"후딩스","link":"https://magazine.musinsa.com/index.php?m=shopstaff&_y=2021&ordw=d_regis&p=1&uid=167661","retrieved":1635241734332,"image":"https://image.musinsa.com/mfile_s01/_shopstaff/250.staff_6177b779715c4.jpg?20211026175114"},{"title":"김보라","contents":"샐러드볼즈","link":"https://magazine.musinsa.com/index.php?m=shopstaff&_y=2021&ordw=d_regis&p=1&uid=167660","retrieved":1635241734334,"image":"https://image.musinsa.com/mfile_s01/_shopstaff/250.staff_6177b76dbbd8f.jpg?20211026174927"}]}